{
  "alignments": [],
  "approved_alignment_count": 0,
  "asset_id": "asset_958e3609070428df6903dfba",
  "bibliographic_verified": false,
  "content_nodes": [
    {
      "confidence": 0.98,
      "end_pdf_page": 1,
      "end_printed_page": null,
      "evidence_span_ids": [],
      "kind": "page",
      "level": 0,
      "node_id": "tcn_8444e0c5af5bcf87",
      "parent_id": null,
      "pdf_page": 1,
      "printed_page": null,
      "review_status": "machine_checked",
      "source": "pdfjs_text_layer",
      "title": "PDF 第 1 页",
      "unit_id": null
    },
    {
      "confidence": 0.98,
      "end_pdf_page": 2,
      "end_printed_page": null,
      "evidence_span_ids": [],
      "kind": "page",
      "level": 0,
      "node_id": "tcn_1ab6d0095e37fa78",
      "parent_id": null,
      "pdf_page": 2,
      "printed_page": null,
      "review_status": "machine_checked",
      "source": "pdfjs_text_layer",
      "title": "PDF 第 2 页",
      "unit_id": null
    },
    {
      "confidence": 0.98,
      "end_pdf_page": 3,
      "end_printed_page": null,
      "evidence_span_ids": [],
      "kind": "page",
      "level": 0,
      "node_id": "tcn_e88bdd4694e30c36",
      "parent_id": null,
      "pdf_page": 3,
      "printed_page": null,
      "review_status": "machine_checked",
      "source": "pdfjs_text_layer",
      "title": "PDF 第 3 页",
      "unit_id": null
    },
    {
      "confidence": 0.98,
      "end_pdf_page": 4,
      "end_printed_page": null,
      "evidence_span_ids": [],
      "kind": "page",
      "level": 0,
      "node_id": "tcn_8b6d869df9805fd0",
      "parent_id": "tcn_d3dfb17b45185d69",
      "pdf_page": 4,
      "printed_page": null,
      "review_status": "machine_checked",
      "source": "pdfjs_text_layer",
      "title": "PDF 第 4 页",
      "unit_id": "tcu_7cedb850b44b47c9"
    },
    {
      "confidence": 0.92,
      "end_pdf_page": 50,
      "end_printed_page": null,
      "evidence_span_ids": [],
      "kind": "section",
      "level": 0,
      "node_id": "tcn_d3dfb17b45185d69",
      "parent_id": null,
      "pdf_page": 4,
      "printed_page": null,
      "review_status": "approved",
      "source": "verified_toc",
      "text_excerpt": "403.34 平方米,画面高 4.26 米,全长 94.68 米,共画天神 286 身,描绘了",
      "title": "403.34 平方米,画面高 4.26 米,全长 94.68 米,共画天神 286 身,描绘了",
      "toc_entry_id": "tcu_7cedb850b44b47c9",
      "unit_id": "tcu_7cedb850b44b47c9"
    },
    {
      "confidence": 0.98,
      "end_pdf_page": 5,
      "end_printed_page": "1",
      "evidence_span_ids": [],
      "kind": "page",
      "level": 0,
      "node_id": "tcn_14665c84d6791fb2",
      "parent_id": "tcn_d3dfb17b45185d69",
      "pdf_page": 5,
      "printed_page": "1",
      "review_status": "machine_checked",
      "source": "pdfjs_text_layer",
      "title": "PDF 第 5 页",
      "unit_id": "tcu_7cedb850b44b47c9"
    },
    {
      "confidence": 0.98,
      "end_pdf_page": 6,
      "end_printed_page": "2",
      "evidence_span_ids": [],
      "kind": "page",
      "level": 0,
      "node_id": "tcn_0a06b9cc7a99b8a7",
      "parent_id": "tcn_d3dfb17b45185d69",
      "pdf_page": 6,
      "printed_page": "2",
      "review_status": "machine_checked",
      "source": "pdfjs_text_layer",
      "title": "PDF 第 6 页",
      "unit_id": "tcu_7cedb850b44b47c9"
    },
    {
      "confidence": 0.98,
      "end_pdf_page": 7,
      "end_printed_page": "3",
      "evidence_span_ids": [],
      "kind": "page",
      "level": 0,
      "node_id": "tcn_5bfe66f45e30a0df",
      "parent_id": "tcn_d3dfb17b45185d69",
      "pdf_page": 7,
      "printed_page": "3",
      "review_status": "machine_checked",
      "source": "pdfjs_text_layer",
      "title": "PDF 第 7 页",
      "unit_id": "tcu_7cedb850b44b47c9"
    },
    {
      "confidence": 0.9,
      "end_pdf_page": 10,
      "end_printed_page": "4",
      "evidence_span_ids": [
        "tes_64691855c50881dd"
      ],
      "kind": "lesson",
      "level": 0,
      "node_id": "tcn_e02ff65c99144bf9",
      "parent_id": "tcn_d3dfb17b45185d69",
      "pdf_page": 8,
      "printed_page": "4",
      "review_status": "machine_checked",
      "source": "body_heading",
      "text_excerpt": "2. 你能说出色相环中的颜色哪些",
      "title": "2你能说出色相环中的颜色哪些",
      "unit_id": "tcu_7cedb850b44b47c9"
    },
    {
      "confidence": 0.98,
      "end_pdf_page": 8,
      "end_printed_page": "4",
      "evidence_span_ids": [],
      "kind": "page",
      "level": 0,
      "node_id": "tcn_31944e835ad80fcc",
      "parent_id": "tcn_d3dfb17b45185d69",
      "pdf_page": 8,
      "printed_page": "4",
      "review_status": "machine_checked",
      "source": "pdfjs_text_layer",
      "title": "PDF 第 8 页",
      "unit_id": "tcu_7cedb850b44b47c9"
    },
    {
      "confidence": 0.98,
      "end_pdf_page": 9,
      "end_printed_page": "5",
      "evidence_span_ids": [],
      "kind": "page",
      "level": 0,
      "node_id": "tcn_45204d70e3271268",
      "parent_id": "tcn_d3dfb17b45185d69",
      "pdf_page": 9,
      "printed_page": "5",
      "review_status": "machine_checked",
      "source": "pdfjs_text_layer",
      "title": "PDF 第 9 页",
      "unit_id": "tcu_7cedb850b44b47c9"
    },
    {
      "confidence": 0.98,
      "end_pdf_page": 10,
      "end_printed_page": "6",
      "evidence_span_ids": [],
      "kind": "page",
      "level": 0,
      "node_id": "tcn_173c7b6e0db34bf3",
      "parent_id": "tcn_d3dfb17b45185d69",
      "pdf_page": 10,
      "printed_page": "6",
      "review_status": "machine_checked",
      "source": "pdfjs_text_layer",
      "title": "PDF 第 10 页",
      "unit_id": "tcu_7cedb850b44b47c9"
    },
    {
      "confidence": 0.9,
      "end_pdf_page": 11,
      "end_printed_page": "7",
      "evidence_span_ids": [
        "tes_e19d10c2b4cca4aa"
      ],
      "kind": "lesson",
      "level": 0,
      "node_id": "tcn_95de92297909df1b",
      "parent_id": "tcn_d3dfb17b45185d69",
      "pdf_page": 11,
      "printed_page": "7",
      "review_status": "machine_checked",
      "source": "body_heading",
      "text_excerpt": "2. 欣赏《阿西",
      "title": "2欣赏《阿西",
      "unit_id": "tcu_7cedb850b44b47c9"
    },
    {
      "confidence": 0.98,
      "end_pdf_page": 11,
      "end_printed_page": "7",
      "evidence_span_ids": [],
      "kind": "page",
      "level": 0,
      "node_id": "tcn_dd107b075aaf177a",
      "parent_id": "tcn_d3dfb17b45185d69",
      "pdf_page": 11,
      "printed_page": "7",
      "review_status": "machine_checked",
      "source": "pdfjs_text_layer",
      "title": "PDF 第 11 页",
      "unit_id": "tcu_7cedb850b44b47c9"
    },
    {
      "confidence": 0.9,
      "end_pdf_page": 13,
      "end_printed_page": "8",
      "evidence_span_ids": [
        "tes_3e0939894c472872"
      ],
      "kind": "lesson",
      "level": 0,
      "node_id": "tcn_466ad6e54537267d",
      "parent_id": "tcn_d3dfb17b45185d69",
      "pdf_page": 12,
      "printed_page": "8",
      "review_status": "machine_checked",
      "source": "body_heading",
      "text_excerpt": "88 航天飞机",
      "title": "88航天飞机",
      "unit_id": "tcu_7cedb850b44b47c9"
    },
    {
      "confidence": 0.98,
      "end_pdf_page": 12,
      "end_printed_page": "8",
      "evidence_span_ids": [],
      "kind": "page",
      "level": 0,
      "node_id": "tcn_555795376b0f456e",
      "parent_id": "tcn_d3dfb17b45185d69",
      "pdf_page": 12,
      "printed_page": "8",
      "review_status": "machine_checked",
      "source": "pdfjs_text_layer",
      "title": "PDF 第 12 页",
      "unit_id": "tcu_7cedb850b44b47c9"
    },
    {
      "confidence": 0.98,
      "end_pdf_page": 13,
      "end_printed_page": "9",
      "evidence_span_ids": [],
      "kind": "page",
      "level": 0,
      "node_id": "tcn_eb2e17765f87103f",
      "parent_id": "tcn_d3dfb17b45185d69",
      "pdf_page": 13,
      "printed_page": "9",
      "review_status": "machine_checked",
      "source": "pdfjs_text_layer",
      "title": "PDF 第 13 页",
      "unit_id": "tcu_7cedb850b44b47c9"
    },
    {
      "confidence": 0.9,
      "end_pdf_page": 14,
      "end_printed_page": "10",
      "evidence_span_ids": [
        "tes_7a5819708c7c8136"
      ],
      "kind": "lesson",
      "level": 0,
      "node_id": "tcn_308bc83622e6ad37",
      "parent_id": "tcn_d3dfb17b45185d69",
      "pdf_page": 14,
      "printed_page": "10",
      "review_status": "machine_checked",
      "source": "body_heading",
      "text_excerpt": "1. 哪些工具会在刮蜡纸上留下",
      "title": "1哪些工具会在刮蜡纸上留下",
      "unit_id": "tcu_7cedb850b44b47c9"
    },
    {
      "confidence": 0.9,
      "end_pdf_page": 17,
      "end_printed_page": "10",
      "evidence_span_ids": [
        "tes_63a98e4891e8d3c2"
      ],
      "kind": "lesson",
      "level": 0,
      "node_id": "tcn_89cb08e40c9933df",
      "parent_id": "tcn_d3dfb17b45185d69",
      "pdf_page": 14,
      "printed_page": "10",
      "review_status": "machine_checked",
      "source": "body_heading",
      "text_excerpt": "4. 学生作品在刮蜡画的创作方",
      "title": "4学生作品在刮蜡画的创作方",
      "unit_id": "tcu_7cedb850b44b47c9"
    },
    {
      "confidence": 0.98,
      "end_pdf_page": 14,
      "end_printed_page": "10",
      "evidence_span_ids": [],
      "kind": "page",
      "level": 0,
      "node_id": "tcn_7bfafb16a4e99ce7",
      "parent_id": "tcn_d3dfb17b45185d69",
      "pdf_page": 14,
      "printed_page": "10",
      "review_status": "machine_checked",
      "source": "pdfjs_text_layer",
      "title": "PDF 第 14 页",
      "unit_id": "tcu_7cedb850b44b47c9"
    },
    {
      "confidence": 0.98,
      "end_pdf_page": 15,
      "end_printed_page": "11",
      "evidence_span_ids": [],
      "kind": "page",
      "level": 0,
      "node_id": "tcn_3483bb1bc261419a",
      "parent_id": "tcn_d3dfb17b45185d69",
      "pdf_page": 15,
      "printed_page": "11",
      "review_status": "machine_checked",
      "source": "pdfjs_text_layer",
      "title": "PDF 第 15 页",
      "unit_id": "tcu_7cedb850b44b47c9"
    },
    {
      "confidence": 0.98,
      "end_pdf_page": 16,
      "end_printed_page": "12",
      "evidence_span_ids": [],
      "kind": "page",
      "level": 0,
      "node_id": "tcn_c6149c7468358649",
      "parent_id": "tcn_d3dfb17b45185d69",
      "pdf_page": 16,
      "printed_page": "12",
      "review_status": "machine_checked",
      "source": "pdfjs_text_layer",
      "title": "PDF 第 16 页",
      "unit_id": "tcu_7cedb850b44b47c9"
    },
    {
      "confidence": 0.98,
      "end_pdf_page": 17,
      "end_printed_page": "13",
      "evidence_span_ids": [],
      "kind": "page",
      "level": 0,
      "node_id": "tcn_89d7cc8f83d81534",
      "parent_id": "tcn_d3dfb17b45185d69",
      "pdf_page": 17,
      "printed_page": "13",
      "review_status": "machine_checked",
      "source": "pdfjs_text_layer",
      "title": "PDF 第 17 页",
      "unit_id": "tcu_7cedb850b44b47c9"
    },
    {
      "confidence": 0.9,
      "end_pdf_page": 18,
      "end_printed_page": "14",
      "evidence_span_ids": [
        "tes_2debb332c0d03ee8"
      ],
      "kind": "lesson",
      "level": 0,
      "node_id": "tcn_0f020261648d7695",
      "parent_id": "tcn_d3dfb17b45185d69",
      "pdf_page": 18,
      "printed_page": "14",
      "review_status": "machine_checked",
      "source": "body_heading",
      "text_excerpt": "3. 飞天凌空飞舞的动势是凭借",
      "title": "3飞天凌空飞舞的动势是凭借",
      "unit_id": "tcu_7cedb850b44b47c9"
    },
    {
      "confidence": 0.9,
      "end_pdf_page": 20,
      "end_printed_page": "14",
      "evidence_span_ids": [
        "tes_2492544a8c9fc9e6"
      ],
      "kind": "lesson",
      "level": 0,
      "node_id": "tcn_236078e4eeb62bbc",
      "parent_id": "tcn_d3dfb17b45185d69",
      "pdf_page": 18,
      "printed_page": "14",
      "review_status": "machine_checked",
      "source": "body_heading",
      "text_excerpt": "1. 课中的飞天作品给你哪些感",
      "title": "1课中的飞天作品给你哪些感",
      "unit_id": "tcu_7cedb850b44b47c9"
    },
    {
      "confidence": 0.98,
      "end_pdf_page": 18,
      "end_printed_page": "14",
      "evidence_span_ids": [],
      "kind": "page",
      "level": 0,
      "node_id": "tcn_5f841b45870e251e",
      "parent_id": "tcn_d3dfb17b45185d69",
      "pdf_page": 18,
      "printed_page": "14",
      "review_status": "machine_checked",
      "source": "pdfjs_text_layer",
      "title": "PDF 第 18 页",
      "unit_id": "tcu_7cedb850b44b47c9"
    },
    {
      "confidence": 0.98,
      "end_pdf_page": 19,
      "end_printed_page": "15",
      "evidence_span_ids": [],
      "kind": "page",
      "level": 0,
      "node_id": "tcn_d5154e795af3e5cf",
      "parent_id": "tcn_d3dfb17b45185d69",
      "pdf_page": 19,
      "printed_page": "15",
      "review_status": "machine_checked",
      "source": "pdfjs_text_layer",
      "title": "PDF 第 19 页",
      "unit_id": "tcu_7cedb850b44b47c9"
    },
    {
      "confidence": 0.98,
      "end_pdf_page": 20,
      "end_printed_page": "16",
      "evidence_span_ids": [],
      "kind": "page",
      "level": 0,
      "node_id": "tcn_0b8ce75b55a5ac73",
      "parent_id": "tcn_d3dfb17b45185d69",
      "pdf_page": 20,
      "printed_page": "16",
      "review_status": "machine_checked",
      "source": "pdfjs_text_layer",
      "title": "PDF 第 20 页",
      "unit_id": "tcu_7cedb850b44b47c9"
    },
    {
      "confidence": 0.9,
      "end_pdf_page": 21,
      "end_printed_page": "17",
      "evidence_span_ids": [
        "tes_217e2444383d36e3"
      ],
      "kind": "lesson",
      "level": 0,
      "node_id": "tcn_1f5f24d814eb13c4",
      "parent_id": "tcn_d3dfb17b45185d69",
      "pdf_page": 21,
      "printed_page": "17",
      "review_status": "machine_checked",
      "source": "body_heading",
      "text_excerpt": "1. 表现飞天动势的线",
      "title": "1表现飞天动势的线",
      "unit_id": "tcu_7cedb850b44b47c9"
    },
    {
      "confidence": 0.9,
      "end_pdf_page": 21,
      "end_printed_page": "17",
      "evidence_span_ids": [
        "tes_056cefe0b1d60032"
      ],
      "kind": "lesson",
      "level": 0,
      "node_id": "tcn_d27e18616546e508",
      "parent_id": "tcn_d3dfb17b45185d69",
      "pdf_page": 21,
      "printed_page": "17",
      "review_status": "machine_checked",
      "source": "body_heading",
      "text_excerpt": "3. 你想创作一幅什么",
      "title": "3你想创作一幅什么",
      "unit_id": "tcu_7cedb850b44b47c9"
    },
    {
      "confidence": 0.9,
      "end_pdf_page": 25,
      "end_printed_page": "17",
      "evidence_span_ids": [
        "tes_9ef6bfc4581d14b7"
      ],
      "kind": "lesson",
      "level": 0,
      "node_id": "tcn_d35f3405b772f944",
      "parent_id": "tcn_d3dfb17b45185d69",
      "pdf_page": 21,
      "printed_page": "17",
      "review_status": "machine_checked",
      "source": "body_heading",
      "text_excerpt": "2. 飘带与人物的动势",
      "title": "2飘带与人物的动势",
      "unit_id": "tcu_7cedb850b44b47c9"
    },
    {
      "confidence": 0.98,
      "end_pdf_page": 21,
      "end_printed_page": "17",
      "evidence_span_ids": [],
      "kind": "page",
      "level": 0,
      "node_id": "tcn_e0e5b061260852be",
      "parent_id": "tcn_d3dfb17b45185d69",
      "pdf_page": 21,
      "printed_page": "17",
      "review_status": "machine_checked",
      "source": "pdfjs_text_layer",
      "title": "PDF 第 21 页",
      "unit_id": "tcu_7cedb850b44b47c9"
    },
    {
      "confidence": 0.98,
      "end_pdf_page": 22,
      "end_printed_page": "18",
      "evidence_span_ids": [],
      "kind": "page",
      "level": 0,
      "node_id": "tcn_2d25859863eb50cf",
      "parent_id": "tcn_d3dfb17b45185d69",
      "pdf_page": 22,
      "printed_page": "18",
      "review_status": "machine_checked",
      "source": "pdfjs_text_layer",
      "title": "PDF 第 22 页",
      "unit_id": "tcu_7cedb850b44b47c9"
    },
    {
      "confidence": 0.86,
      "end_pdf_page": 23,
      "end_printed_page": "19",
      "evidence_span_ids": [
        "tes_466841752152586e"
      ],
      "kind": "exercise",
      "level": 0,
      "node_id": "tcn_a1d8c57771367374",
      "parent_id": "tcn_d27e18616546e508",
      "pdf_page": 23,
      "printed_page": "19",
      "review_status": "machine_checked",
      "source": "task_verb_pattern",
      "text_excerpt": "根据对生活中笔的观察,了解笔的每个部分的功能,并且自己设计一支新颖实用的笔。",
      "title": "根据对生活中笔的观察,了解笔的每个部分的功能,并且自己设计一支新颖实用的笔。",
      "unit_id": "tcu_7cedb850b44b47c9"
    },
    {
      "confidence": 0.98,
      "end_pdf_page": 23,
      "end_printed_page": "19",
      "evidence_span_ids": [],
      "kind": "page",
      "level": 0,
      "node_id": "tcn_4131dd9a265f2bdc",
      "parent_id": "tcn_d3dfb17b45185d69",
      "pdf_page": 23,
      "printed_page": "19",
      "review_status": "machine_checked",
      "source": "pdfjs_text_layer",
      "title": "PDF 第 23 页",
      "unit_id": "tcu_7cedb850b44b47c9"
    },
    {
      "confidence": 0.98,
      "end_pdf_page": 24,
      "end_printed_page": "20",
      "evidence_span_ids": [],
      "kind": "page",
      "level": 0,
      "node_id": "tcn_7b62e153ced9821f",
      "parent_id": "tcn_d3dfb17b45185d69",
      "pdf_page": 24,
      "printed_page": "20",
      "review_status": "machine_checked",
      "source": "pdfjs_text_layer",
      "title": "PDF 第 24 页",
      "unit_id": "tcu_7cedb850b44b47c9"
    },
    {
      "confidence": 0.98,
      "end_pdf_page": 25,
      "end_printed_page": "21",
      "evidence_span_ids": [],
      "kind": "page",
      "level": 0,
      "node_id": "tcn_14d117f7b0da48ab",
      "parent_id": "tcn_d3dfb17b45185d69",
      "pdf_page": 25,
      "printed_page": "21",
      "review_status": "machine_checked",
      "source": "pdfjs_text_layer",
      "title": "PDF 第 25 页",
      "unit_id": "tcu_7cedb850b44b47c9"
    },
    {
      "confidence": 0.9,
      "end_pdf_page": 26,
      "end_printed_page": "22",
      "evidence_span_ids": [
        "tes_a0c17a1b79175ccf"
      ],
      "kind": "lesson",
      "level": 0,
      "node_id": "tcn_5914696396491ff1",
      "parent_id": "tcn_d3dfb17b45185d69",
      "pdf_page": 26,
      "printed_page": "22",
      "review_status": "machine_checked",
      "source": "body_heading",
      "text_excerpt": "2. 你认为本课中",
      "title": "2你认为本课中",
      "unit_id": "tcu_7cedb850b44b47c9"
    },
    {
      "confidence": 0.9,
      "end_pdf_page": 27,
      "end_printed_page": "22",
      "evidence_span_ids": [
        "tes_2468eaa68eb48bac"
      ],
      "kind": "lesson",
      "level": 0,
      "node_id": "tcn_8c57fc97c141b961",
      "parent_id": "tcn_d3dfb17b45185d69",
      "pdf_page": 26,
      "printed_page": "22",
      "review_status": "machine_checked",
      "source": "body_heading",
      "text_excerpt": "1. 用什么样的线",
      "title": "1用什么样的线",
      "unit_id": "tcu_7cedb850b44b47c9"
    },
    {
      "confidence": 0.98,
      "end_pdf_page": 26,
      "end_printed_page": "22",
      "evidence_span_ids": [],
      "kind": "page",
      "level": 0,
      "node_id": "tcn_b32f28af6c8d3f38",
      "parent_id": "tcn_d3dfb17b45185d69",
      "pdf_page": 26,
      "printed_page": "22",
      "review_status": "machine_checked",
      "source": "pdfjs_text_layer",
      "title": "PDF 第 26 页",
      "unit_id": "tcu_7cedb850b44b47c9"
    },
    {
      "confidence": 0.98,
      "end_pdf_page": 27,
      "end_printed_page": "23",
      "evidence_span_ids": [],
      "kind": "page",
      "level": 0,
      "node_id": "tcn_739655fb0a4f646e",
      "parent_id": "tcn_d3dfb17b45185d69",
      "pdf_page": 27,
      "printed_page": "23",
      "review_status": "machine_checked",
      "source": "pdfjs_text_layer",
      "title": "PDF 第 27 页",
      "unit_id": "tcu_7cedb850b44b47c9"
    },
    {
      "confidence": 0.9,
      "end_pdf_page": 33,
      "end_printed_page": "24",
      "evidence_span_ids": [
        "tes_0fffb18ba0dacda1"
      ],
      "kind": "lesson",
      "level": 0,
      "node_id": "tcn_bf883430b056af76",
      "parent_id": "tcn_d3dfb17b45185d69",
      "pdf_page": 28,
      "printed_page": "24",
      "review_status": "machine_checked",
      "source": "body_heading",
      "text_excerpt": "2. 这些形象有",
      "title": "2这些形象有",
      "unit_id": "tcu_7cedb850b44b47c9"
    },
    {
      "confidence": 0.98,
      "end_pdf_page": 28,
      "end_printed_page": "24",
      "evidence_span_ids": [],
      "kind": "page",
      "level": 0,
      "node_id": "tcn_08d4f236959127b9",
      "parent_id": "tcn_d3dfb17b45185d69",
      "pdf_page": 28,
      "printed_page": "24",
      "review_status": "machine_checked",
      "source": "pdfjs_text_layer",
      "title": "PDF 第 28 页",
      "unit_id": "tcu_7cedb850b44b47c9"
    },
    {
      "confidence": 0.98,
      "end_pdf_page": 29,
      "end_printed_page": "25",
      "evidence_span_ids": [],
      "kind": "page",
      "level": 0,
      "node_id": "tcn_c804beb1459c82e5",
      "parent_id": "tcn_d3dfb17b45185d69",
      "pdf_page": 29,
      "printed_page": "25",
      "review_status": "machine_checked",
      "source": "pdfjs_text_layer",
      "title": "PDF 第 29 页",
      "unit_id": "tcu_7cedb850b44b47c9"
    },
    {
      "confidence": 0.98,
      "end_pdf_page": 30,
      "end_printed_page": "26",
      "evidence_span_ids": [],
      "kind": "page",
      "level": 0,
      "node_id": "tcn_2a8e25e8390d1ea1",
      "parent_id": "tcn_d3dfb17b45185d69",
      "pdf_page": 30,
      "printed_page": "26",
      "review_status": "machine_checked",
      "source": "pdfjs_text_layer",
      "title": "PDF 第 30 页",
      "unit_id": "tcu_7cedb850b44b47c9"
    },
    {
      "confidence": 0.98,
      "end_pdf_page": 31,
      "end_printed_page": "27",
      "evidence_span_ids": [],
      "kind": "page",
      "level": 0,
      "node_id": "tcn_e26088118c302c63",
      "parent_id": "tcn_d3dfb17b45185d69",
      "pdf_page": 31,
      "printed_page": "27",
      "review_status": "machine_checked",
      "source": "pdfjs_text_layer",
      "title": "PDF 第 31 页",
      "unit_id": "tcu_7cedb850b44b47c9"
    },
    {
      "confidence": 0.86,
      "end_pdf_page": 32,
      "end_printed_page": "28",
      "evidence_span_ids": [
        "tes_89e92c5152da64ca"
      ],
      "kind": "exercise",
      "level": 0,
      "node_id": "tcn_2f51e90600be61aa",
      "parent_id": "tcn_bf883430b056af76",
      "pdf_page": 32,
      "printed_page": "28",
      "review_status": "machine_checked",
      "source": "task_verb_pattern",
      "text_excerpt": "结合,为自己设计一个美观的靠垫。",
      "title": "结合,为自己设计一个美观的靠垫。",
      "unit_id": "tcu_7cedb850b44b47c9"
    },
    {
      "confidence": 0.98,
      "end_pdf_page": 32,
      "end_printed_page": "28",
      "evidence_span_ids": [],
      "kind": "page",
      "level": 0,
      "node_id": "tcn_c0d6c82e7286b4b8",
      "parent_id": "tcn_d3dfb17b45185d69",
      "pdf_page": 32,
      "printed_page": "28",
      "review_status": "machine_checked",
      "source": "pdfjs_text_layer",
      "title": "PDF 第 32 页",
      "unit_id": "tcu_7cedb850b44b47c9"
    },
    {
      "confidence": 0.98,
      "end_pdf_page": 33,
      "end_printed_page": "29",
      "evidence_span_ids": [],
      "kind": "page",
      "level": 0,
      "node_id": "tcn_49abe630365b942a",
      "parent_id": "tcn_d3dfb17b45185d69",
      "pdf_page": 33,
      "printed_page": "29",
      "review_status": "machine_checked",
      "source": "pdfjs_text_layer",
      "title": "PDF 第 33 页",
      "unit_id": "tcu_7cedb850b44b47c9"
    },
    {
      "confidence": 0.9,
      "end_pdf_page": 36,
      "end_printed_page": "30",
      "evidence_span_ids": [
        "tes_1af1ec587725a688"
      ],
      "kind": "lesson",
      "level": 0,
      "node_id": "tcn_593364283d74696d",
      "parent_id": "tcn_d3dfb17b45185d69",
      "pdf_page": 34,
      "printed_page": "30",
      "review_status": "machine_checked",
      "source": "body_heading",
      "text_excerpt": "2. 伞的各部分应该如",
      "title": "2伞的各部分应该如",
      "unit_id": "tcu_7cedb850b44b47c9"
    },
    {
      "confidence": 0.98,
      "end_pdf_page": 34,
      "end_printed_page": "30",
      "evidence_span_ids": [],
      "kind": "page",
      "level": 0,
      "node_id": "tcn_420423ebc63d2a52",
      "parent_id": "tcn_d3dfb17b45185d69",
      "pdf_page": 34,
      "printed_page": "30",
      "review_status": "machine_checked",
      "source": "pdfjs_text_layer",
      "title": "PDF 第 34 页",
      "unit_id": "tcu_7cedb850b44b47c9"
    },
    {
      "confidence": 0.86,
      "end_pdf_page": 35,
      "end_printed_page": "31",
      "evidence_span_ids": [
        "tes_8ca0fd8777aaf811"
      ],
      "kind": "exercise",
      "level": 0,
      "node_id": "tcn_9d7d71990f0c0e44",
      "parent_id": "tcn_593364283d74696d",
      "pdf_page": 35,
      "printed_page": "31",
      "review_status": "machine_checked",
      "source": "task_verb_pattern",
      "text_excerpt": "设计并制作一只漂亮的小降落伞。做好后,拿到外面试一试,看看",
      "title": "设计并制作一只漂亮的小降落伞。做好后,拿到外面试一试,看看",
      "unit_id": "tcu_7cedb850b44b47c9"
    },
    {
      "confidence": 0.98,
      "end_pdf_page": 35,
      "end_printed_page": "31",
      "evidence_span_ids": [],
      "kind": "page",
      "level": 0,
      "node_id": "tcn_e9df0bc081afeb68",
      "parent_id": "tcn_d3dfb17b45185d69",
      "pdf_page": 35,
      "printed_page": "31",
      "review_status": "machine_checked",
      "source": "pdfjs_text_layer",
      "title": "PDF 第 35 页",
      "unit_id": "tcu_7cedb850b44b47c9"
    },
    {
      "confidence": 0.98,
      "end_pdf_page": 36,
      "end_printed_page": "32",
      "evidence_span_ids": [],
      "kind": "page",
      "level": 0,
      "node_id": "tcn_012b146d80a400ed",
      "parent_id": "tcn_d3dfb17b45185d69",
      "pdf_page": 36,
      "printed_page": "32",
      "review_status": "machine_checked",
      "source": "pdfjs_text_layer",
      "title": "PDF 第 36 页",
      "unit_id": "tcu_7cedb850b44b47c9"
    },
    {
      "confidence": 0.9,
      "end_pdf_page": 39,
      "end_printed_page": "33",
      "evidence_span_ids": [
        "tes_5490f544593ce181"
      ],
      "kind": "lesson",
      "level": 0,
      "node_id": "tcn_51fb739856bdb173",
      "parent_id": "tcn_d3dfb17b45185d69",
      "pdf_page": 37,
      "printed_page": "33",
      "review_status": "machine_checked",
      "source": "body_heading",
      "text_excerpt": "2. 你认为学生作品中",
      "title": "2你认为学生作品中",
      "unit_id": "tcu_7cedb850b44b47c9"
    },
    {
      "confidence": 0.98,
      "end_pdf_page": 37,
      "end_printed_page": "33",
      "evidence_span_ids": [],
      "kind": "page",
      "level": 0,
      "node_id": "tcn_2c349bf0eb570f82",
      "parent_id": "tcn_d3dfb17b45185d69",
      "pdf_page": 37,
      "printed_page": "33",
      "review_status": "machine_checked",
      "source": "pdfjs_text_layer",
      "title": "PDF 第 37 页",
      "unit_id": "tcu_7cedb850b44b47c9"
    },
    {
      "confidence": 0.98,
      "end_pdf_page": 38,
      "end_printed_page": "34",
      "evidence_span_ids": [],
      "kind": "page",
      "level": 0,
      "node_id": "tcn_c276bf5d4a8bc7b0",
      "parent_id": "tcn_d3dfb17b45185d69",
      "pdf_page": 38,
      "printed_page": "34",
      "review_status": "machine_checked",
      "source": "pdfjs_text_layer",
      "title": "PDF 第 38 页",
      "unit_id": "tcu_7cedb850b44b47c9"
    },
    {
      "confidence": 0.98,
      "end_pdf_page": 39,
      "end_printed_page": "35",
      "evidence_span_ids": [],
      "kind": "page",
      "level": 0,
      "node_id": "tcn_b84a9a3abdcd5902",
      "parent_id": "tcn_d3dfb17b45185d69",
      "pdf_page": 39,
      "printed_page": "35",
      "review_status": "machine_checked",
      "source": "pdfjs_text_layer",
      "title": "PDF 第 39 页",
      "unit_id": "tcu_7cedb850b44b47c9"
    },
    {
      "confidence": 0.9,
      "end_pdf_page": 40,
      "end_printed_page": "36",
      "evidence_span_ids": [
        "tes_adaff8679f1afebd"
      ],
      "kind": "lesson",
      "level": 0,
      "node_id": "tcn_209b69e3934ef7c7",
      "parent_id": "tcn_d3dfb17b45185d69",
      "pdf_page": 40,
      "printed_page": "36",
      "review_status": "machine_checked",
      "source": "body_heading",
      "text_excerpt": "2. 本课刻印方法中",
      "title": "2本课刻印方法中",
      "unit_id": "tcu_7cedb850b44b47c9"
    },
    {
      "confidence": 0.9,
      "end_pdf_page": 40,
      "end_printed_page": "36",
      "evidence_span_ids": [
        "tes_2d73dd717e6e5e89"
      ],
      "kind": "lesson",
      "level": 0,
      "node_id": "tcn_54bfdf7c5aaf5e77",
      "parent_id": "tcn_d3dfb17b45185d69",
      "pdf_page": 40,
      "printed_page": "36",
      "review_status": "machine_checked",
      "source": "body_heading",
      "text_excerpt": "1. 生活中的哪些材",
      "title": "1生活中的哪些材",
      "unit_id": "tcu_7cedb850b44b47c9"
    },
    {
      "confidence": 0.9,
      "end_pdf_page": 40,
      "end_printed_page": "36",
      "evidence_span_ids": [
        "tes_8656de4512ee6f0a"
      ],
      "kind": "lesson",
      "level": 0,
      "node_id": "tcn_57575faabac63e4f",
      "parent_id": "tcn_d3dfb17b45185d69",
      "pdf_page": 40,
      "printed_page": "36",
      "review_status": "machine_checked",
      "source": "body_heading",
      "text_excerpt": "3. 刻字时有什么小",
      "title": "3刻字时有什么小",
      "unit_id": "tcu_7cedb850b44b47c9"
    },
    {
      "confidence": 0.9,
      "end_pdf_page": 41,
      "end_printed_page": "36",
      "evidence_span_ids": [
        "tes_15867ddbf39ac78f"
      ],
      "kind": "lesson",
      "level": 0,
      "node_id": "tcn_72ee9bdeec7f5309",
      "parent_id": "tcn_d3dfb17b45185d69",
      "pdf_page": 40,
      "printed_page": "36",
      "review_status": "machine_checked",
      "source": "body_heading",
      "text_excerpt": "2 上色",
      "title": "2上色",
      "unit_id": "tcu_7cedb850b44b47c9"
    },
    {
      "confidence": 0.98,
      "end_pdf_page": 40,
      "end_printed_page": "36",
      "evidence_span_ids": [],
      "kind": "page",
      "level": 0,
      "node_id": "tcn_d963038ca7125038",
      "parent_id": "tcn_d3dfb17b45185d69",
      "pdf_page": 40,
      "printed_page": "36",
      "review_status": "machine_checked",
      "source": "pdfjs_text_layer",
      "title": "PDF 第 40 页",
      "unit_id": "tcu_7cedb850b44b47c9"
    },
    {
      "confidence": 0.86,
      "end_pdf_page": 41,
      "end_printed_page": "37",
      "evidence_span_ids": [
        "tes_16b4ded7a3949a3c"
      ],
      "kind": "exercise",
      "level": 0,
      "node_id": "tcn_d2e54e4a05defe84",
      "parent_id": "tcn_72ee9bdeec7f5309",
      "pdf_page": 41,
      "printed_page": "37",
      "review_status": "machine_checked",
      "source": "task_verb_pattern",
      "text_excerpt": "选择适合的材料、图 案、 文 字, 用 刻 印书签",
      "title": "选择适合的材料、图 案、 文 字, 用 刻 印书签",
      "unit_id": "tcu_7cedb850b44b47c9"
    },
    {
      "confidence": 0.98,
      "end_pdf_page": 41,
      "end_printed_page": "37",
      "evidence_span_ids": [],
      "kind": "page",
      "level": 0,
      "node_id": "tcn_7337577ea1f11f52",
      "parent_id": "tcn_d3dfb17b45185d69",
      "pdf_page": 41,
      "printed_page": "37",
      "review_status": "machine_checked",
      "source": "pdfjs_text_layer",
      "title": "PDF 第 41 页",
      "unit_id": "tcu_7cedb850b44b47c9"
    },
    {
      "confidence": 0.86,
      "end_pdf_page": 42,
      "end_printed_page": "38",
      "evidence_span_ids": [
        "tes_782a3961847cf27f"
      ],
      "kind": "exercise",
      "level": 0,
      "node_id": "tcn_5a0878f9e8867e0e",
      "parent_id": "tcn_72ee9bdeec7f5309",
      "pdf_page": 42,
      "printed_page": "38",
      "review_status": "machine_checked",
      "source": "task_verb_pattern",
      "text_excerpt": "想一想,这两幅作品与我们之前见到的作品有什么不同?说一说,创作方法各有什么特点?",
      "title": "想一想,这两幅作品与我们之前见到的作品有什么不同?说一说,创作方法各有什么特点?",
      "unit_id": "tcu_7cedb850b44b47c9"
    },
    {
      "confidence": 0.9,
      "end_pdf_page": 42,
      "end_printed_page": "38",
      "evidence_span_ids": [
        "tes_60335b9622d1727a"
      ],
      "kind": "lesson",
      "level": 0,
      "node_id": "tcn_06c114510f8bd743",
      "parent_id": "tcn_d3dfb17b45185d69",
      "pdf_page": 42,
      "printed_page": "38",
      "review_status": "machine_checked",
      "source": "body_heading",
      "text_excerpt": "2. 同学们的作品采用了什么",
      "title": "2同学们的作品采用了什么",
      "unit_id": "tcu_7cedb850b44b47c9"
    },
    {
      "confidence": 0.9,
      "end_pdf_page": 43,
      "end_printed_page": "38",
      "evidence_span_ids": [
        "tes_3026308154f8b7da"
      ],
      "kind": "lesson",
      "level": 0,
      "node_id": "tcn_2cc3659af38b7967",
      "parent_id": "tcn_d3dfb17b45185d69",
      "pdf_page": 42,
      "printed_page": "38",
      "review_status": "machine_checked",
      "source": "body_heading",
      "text_excerpt": "3. 你想如何表现你的现在和",
      "title": "3你想如何表现你的现在和",
      "unit_id": "tcu_7cedb850b44b47c9"
    },
    {
      "confidence": 0.98,
      "end_pdf_page": 42,
      "end_printed_page": "38",
      "evidence_span_ids": [],
      "kind": "page",
      "level": 0,
      "node_id": "tcn_20b7109462c5c828",
      "parent_id": "tcn_d3dfb17b45185d69",
      "pdf_page": 42,
      "printed_page": "38",
      "review_status": "machine_checked",
      "source": "pdfjs_text_layer",
      "title": "PDF 第 42 页",
      "unit_id": "tcu_7cedb850b44b47c9"
    },
    {
      "confidence": 0.86,
      "end_pdf_page": 43,
      "end_printed_page": "39",
      "evidence_span_ids": [
        "tes_e170be7b8fbe563e"
      ],
      "kind": "exercise",
      "level": 0,
      "node_id": "tcn_4ec45c5c7b5ae5ea",
      "parent_id": "tcn_2cc3659af38b7967",
      "pdf_page": 43,
      "printed_page": "39",
      "review_status": "machine_checked",
      "source": "task_verb_pattern",
      "text_excerpt": "把它画出来并附上说明文字。",
      "title": "把它画出来并附上说明文字。",
      "unit_id": "tcu_7cedb850b44b47c9"
    },
    {
      "confidence": 0.98,
      "end_pdf_page": 43,
      "end_printed_page": "39",
      "evidence_span_ids": [],
      "kind": "page",
      "level": 0,
      "node_id": "tcn_dfed261ba651fd08",
      "parent_id": "tcn_d3dfb17b45185d69",
      "pdf_page": 43,
      "printed_page": "39",
      "review_status": "machine_checked",
      "source": "pdfjs_text_layer",
      "title": "PDF 第 43 页",
      "unit_id": "tcu_7cedb850b44b47c9"
    },
    {
      "confidence": 0.9,
      "end_pdf_page": 45,
      "end_printed_page": "40",
      "evidence_span_ids": [
        "tes_1c44cb9891e14a56"
      ],
      "kind": "lesson",
      "level": 0,
      "node_id": "tcn_5a2d3cae7e8523e2",
      "parent_id": "tcn_d3dfb17b45185d69",
      "pdf_page": 44,
      "printed_page": "40",
      "review_status": "machine_checked",
      "source": "body_heading",
      "text_excerpt": "3. 学生作品中的",
      "title": "3学生作品中的",
      "unit_id": "tcu_7cedb850b44b47c9"
    },
    {
      "confidence": 0.98,
      "end_pdf_page": 44,
      "end_printed_page": "40",
      "evidence_span_ids": [],
      "kind": "page",
      "level": 0,
      "node_id": "tcn_0555e85eba8c7e79",
      "parent_id": "tcn_d3dfb17b45185d69",
      "pdf_page": 44,
      "printed_page": "40",
      "review_status": "machine_checked",
      "source": "pdfjs_text_layer",
      "title": "PDF 第 44 页",
      "unit_id": "tcu_7cedb850b44b47c9"
    },
    {
      "confidence": 0.86,
      "end_pdf_page": 45,
      "end_printed_page": "41",
      "evidence_span_ids": [
        "tes_063901b0147a1683"
      ],
      "kind": "exercise",
      "level": 0,
      "node_id": "tcn_1144700c92fdc4ab",
      "parent_id": "tcn_5a2d3cae7e8523e2",
      "pdf_page": 45,
      "printed_page": "41",
      "review_status": "machine_checked",
      "source": "task_verb_pattern",
      "text_excerpt": "制作一艘能浮在水面上的新颖美观的船,做好后和大家一起将船放到水",
      "title": "制作一艘能浮在水面上的新颖美观的船,做好后和大家一起将船放到水",
      "unit_id": "tcu_7cedb850b44b47c9"
    },
    {
      "confidence": 0.98,
      "end_pdf_page": 45,
      "end_printed_page": "41",
      "evidence_span_ids": [],
      "kind": "page",
      "level": 0,
      "node_id": "tcn_5188eddac689e1d0",
      "parent_id": "tcn_d3dfb17b45185d69",
      "pdf_page": 45,
      "printed_page": "41",
      "review_status": "machine_checked",
      "source": "pdfjs_text_layer",
      "title": "PDF 第 45 页",
      "unit_id": "tcu_7cedb850b44b47c9"
    },
    {
      "confidence": 0.9,
      "end_pdf_page": 46,
      "end_printed_page": "42",
      "evidence_span_ids": [
        "tes_99de0dda1f55e726"
      ],
      "kind": "lesson",
      "level": 0,
      "node_id": "tcn_13f7912fe04b874b",
      "parent_id": "tcn_d3dfb17b45185d69",
      "pdf_page": 46,
      "printed_page": "42",
      "review_status": "machine_checked",
      "source": "body_heading",
      "text_excerpt": "42 老相机",
      "title": "42老相机",
      "unit_id": "tcu_7cedb850b44b47c9"
    },
    {
      "confidence": 0.98,
      "end_pdf_page": 46,
      "end_printed_page": "42",
      "evidence_span_ids": [],
      "kind": "page",
      "level": 0,
      "node_id": "tcn_c3d8f534e0cc97da",
      "parent_id": "tcn_d3dfb17b45185d69",
      "pdf_page": 46,
      "printed_page": "42",
      "review_status": "machine_checked",
      "source": "pdfjs_text_layer",
      "title": "PDF 第 46 页",
      "unit_id": "tcu_7cedb850b44b47c9"
    },
    {
      "confidence": 0.9,
      "end_pdf_page": 48,
      "end_printed_page": "43",
      "evidence_span_ids": [
        "tes_f826759249783721"
      ],
      "kind": "lesson",
      "level": 0,
      "node_id": "tcn_38fe5976c40b3927",
      "parent_id": "tcn_d3dfb17b45185d69",
      "pdf_page": 47,
      "printed_page": "43",
      "review_status": "machine_checked",
      "source": "body_heading",
      "text_excerpt": "3. 你想如何拍一张主题明确的人像",
      "title": "3你想如何拍一张主题明确的人像",
      "unit_id": "tcu_7cedb850b44b47c9"
    },
    {
      "confidence": 0.98,
      "end_pdf_page": 47,
      "end_printed_page": "43",
      "evidence_span_ids": [],
      "kind": "page",
      "level": 0,
      "node_id": "tcn_bf913f88268e08de",
      "parent_id": "tcn_d3dfb17b45185d69",
      "pdf_page": 47,
      "printed_page": "43",
      "review_status": "machine_checked",
      "source": "pdfjs_text_layer",
      "title": "PDF 第 47 页",
      "unit_id": "tcu_7cedb850b44b47c9"
    },
    {
      "confidence": 0.98,
      "end_pdf_page": 48,
      "end_printed_page": "44",
      "evidence_span_ids": [],
      "kind": "page",
      "level": 0,
      "node_id": "tcn_7ebb88e2de3be7f4",
      "parent_id": "tcn_d3dfb17b45185d69",
      "pdf_page": 48,
      "printed_page": "44",
      "review_status": "machine_checked",
      "source": "pdfjs_text_layer",
      "title": "PDF 第 48 页",
      "unit_id": "tcu_7cedb850b44b47c9"
    },
    {
      "confidence": 0.86,
      "end_pdf_page": 49,
      "end_printed_page": "45",
      "evidence_span_ids": [
        "tes_adf59d04daab690b"
      ],
      "kind": "exercise",
      "level": 0,
      "node_id": "tcn_ebe241df05664c1c",
      "parent_id": "tcn_8007861f625915be",
      "pdf_page": 49,
      "printed_page": "45",
      "review_status": "machine_checked",
      "source": "task_verb_pattern",
      "text_excerpt": "设计制作一个有美好寓意的剪纸作品。",
      "title": "设计制作一个有美好寓意的剪纸作品。",
      "unit_id": "tcu_7cedb850b44b47c9"
    },
    {
      "confidence": 0.9,
      "end_pdf_page": 49,
      "end_printed_page": "45",
      "evidence_span_ids": [
        "tes_c426b0ab89acec2c"
      ],
      "kind": "lesson",
      "level": 0,
      "node_id": "tcn_505d22910172db5c",
      "parent_id": "tcn_d3dfb17b45185d69",
      "pdf_page": 49,
      "printed_page": "45",
      "review_status": "machine_checked",
      "source": "body_heading",
      "text_excerpt": "1. 介绍自己了解的",
      "title": "1介绍自己了解的",
      "unit_id": "tcu_7cedb850b44b47c9"
    },
    {
      "confidence": 0.9,
      "end_pdf_page": 49,
      "end_printed_page": "45",
      "evidence_span_ids": [
        "tes_49484d55cbf6d50b"
      ],
      "kind": "lesson",
      "level": 0,
      "node_id": "tcn_8007861f625915be",
      "parent_id": "tcn_d3dfb17b45185d69",
      "pdf_page": 49,
      "printed_page": "45",
      "review_status": "machine_checked",
      "source": "body_heading",
      "text_excerpt": "3. 你想剪刻一个什",
      "title": "3你想剪刻一个什",
      "unit_id": "tcu_7cedb850b44b47c9"
    },
    {
      "confidence": 0.98,
      "end_pdf_page": 49,
      "end_printed_page": "45",
      "evidence_span_ids": [],
      "kind": "page",
      "level": 0,
      "node_id": "tcn_44b485192071d47b",
      "parent_id": "tcn_d3dfb17b45185d69",
      "pdf_page": 49,
      "printed_page": "45",
      "review_status": "machine_checked",
      "source": "pdfjs_text_layer",
      "title": "PDF 第 49 页",
      "unit_id": "tcu_7cedb850b44b47c9"
    },
    {
      "confidence": 0.9,
      "end_pdf_page": 50,
      "end_printed_page": "46",
      "evidence_span_ids": [
        "tes_a0fb9f3b509f83b5"
      ],
      "kind": "lesson",
      "level": 0,
      "node_id": "tcn_9e0506bc55a540f4",
      "parent_id": "tcn_d3dfb17b45185d69",
      "pdf_page": 50,
      "printed_page": "46",
      "review_status": "machine_checked",
      "source": "body_heading",
      "text_excerpt": "2. 你觉得哪 笔筒",
      "title": "2你觉得哪笔筒",
      "unit_id": "tcu_7cedb850b44b47c9"
    },
    {
      "confidence": 0.98,
      "end_pdf_page": 50,
      "end_printed_page": "46",
      "evidence_span_ids": [],
      "kind": "page",
      "level": 0,
      "node_id": "tcn_64c14f38ab0b0e5d",
      "parent_id": "tcn_d3dfb17b45185d69",
      "pdf_page": 50,
      "printed_page": "46",
      "review_status": "machine_checked",
      "source": "pdfjs_text_layer",
      "title": "PDF 第 50 页",
      "unit_id": "tcu_7cedb850b44b47c9"
    }
  ],
  "edition_id": "ed_26d72869b7188e2196d2",
  "edition_name": "人美版（常锐伦、欧京海）",
  "evidence_id": "ctb_25cc2de0079d",
  "evidence_spans": [
    {
      "bbox": {
        "height": 12,
        "page_height": 737.008,
        "page_width": 524.409,
        "unit": "pdf_point",
        "width": 176.75,
        "x": 322.651,
        "y": 289.543
      },
      "evidence_role": "heading",
      "evidence_span_id": "tes_64691855c50881dd",
      "excerpt": "2. 你能说出色相环中的颜色哪些",
      "excerpt_hash": "555aeb49fa7d3dbd21d1695c6b43046810f651046fe18f84eaac3452196c795f",
      "node_id": "tcn_e02ff65c99144bf9",
      "parser_version": "textbook-content-pdfjs-v3",
      "pdf_page": 8,
      "printed_page": "4",
      "source": "pdfjs_text_layer"
    },
    {
      "bbox": {
        "height": 12,
        "page_height": 737.008,
        "page_width": 524.409,
        "unit": "pdf_point",
        "width": 72.275,
        "x": 409.743,
        "y": 542.385
      },
      "evidence_role": "heading",
      "evidence_span_id": "tes_e19d10c2b4cca4aa",
      "excerpt": "2. 欣赏《阿西",
      "excerpt_hash": "51e2570c6b57f767ab92f02dbfa6f8077819ef3cff43c8aa2cbe822756b79d91",
      "node_id": "tcn_95de92297909df1b",
      "parser_version": "textbook-content-pdfjs-v3",
      "pdf_page": 11,
      "printed_page": "7",
      "source": "pdfjs_text_layer"
    },
    {
      "bbox": {
        "height": 14.1,
        "page_height": 737.008,
        "page_width": 524.409,
        "unit": "pdf_point",
        "width": 259.415,
        "x": 30.884,
        "y": 29.382
      },
      "evidence_role": "heading",
      "evidence_span_id": "tes_3e0939894c472872",
      "excerpt": "88 航天飞机",
      "excerpt_hash": "763072146fed64c10af0d9236b096afb5f577e4c61149c2b534f9e20d31b19b2",
      "node_id": "tcn_466ad6e54537267d",
      "parser_version": "textbook-content-pdfjs-v3",
      "pdf_page": 12,
      "printed_page": "8",
      "source": "pdfjs_text_layer"
    },
    {
      "bbox": {
        "height": 12,
        "page_height": 737.008,
        "page_width": 524.409,
        "unit": "pdf_point",
        "width": 162.644,
        "x": 341.58,
        "y": 51.173
      },
      "evidence_role": "heading",
      "evidence_span_id": "tes_63a98e4891e8d3c2",
      "excerpt": "4. 学生作品在刮蜡画的创作方",
      "excerpt_hash": "1d98759ca1ed68781cc8ea37462460f3d8c7340057f070fb8870670329b91425",
      "node_id": "tcn_89cb08e40c9933df",
      "parser_version": "textbook-content-pdfjs-v3",
      "pdf_page": 14,
      "printed_page": "10",
      "source": "pdfjs_text_layer"
    },
    {
      "bbox": {
        "height": 12,
        "page_height": 737.008,
        "page_width": 524.409,
        "unit": "pdf_point",
        "width": 162.644,
        "x": 341.58,
        "y": 159.173
      },
      "evidence_role": "heading",
      "evidence_span_id": "tes_7a5819708c7c8136",
      "excerpt": "1. 哪些工具会在刮蜡纸上留下",
      "excerpt_hash": "475ea5cf1f10b72b4651792a8d193f8f9ed33b0b68ac05c6becd53a9b46fd455",
      "node_id": "tcn_308bc83622e6ad37",
      "parser_version": "textbook-content-pdfjs-v3",
      "pdf_page": 14,
      "printed_page": "10",
      "source": "pdfjs_text_layer"
    },
    {
      "bbox": {
        "height": 12,
        "page_height": 737.008,
        "page_width": 524.409,
        "unit": "pdf_point",
        "width": 160.171,
        "x": 327.407,
        "y": 399.326
      },
      "evidence_role": "heading",
      "evidence_span_id": "tes_2492544a8c9fc9e6",
      "excerpt": "1. 课中的飞天作品给你哪些感",
      "excerpt_hash": "dc506bf0ec04d0342ce1baf3c8c4a514d1f62f9a83fde7d468675d09ece97583",
      "node_id": "tcn_236078e4eeb62bbc",
      "parser_version": "textbook-content-pdfjs-v3",
      "pdf_page": 18,
      "printed_page": "14",
      "source": "pdfjs_text_layer"
    },
    {
      "bbox": {
        "height": 12,
        "page_height": 737.008,
        "page_width": 524.409,
        "unit": "pdf_point",
        "width": 160.171,
        "x": 327.407,
        "y": 327.326
      },
      "evidence_role": "heading",
      "evidence_span_id": "tes_2debb332c0d03ee8",
      "excerpt": "3. 飞天凌空飞舞的动势是凭借",
      "excerpt_hash": "cfb4b4981b8b47921691995d8200b63d6a772225c1afe933f7191b41bbbf8909",
      "node_id": "tcn_0f020261648d7695",
      "parser_version": "textbook-content-pdfjs-v3",
      "pdf_page": 18,
      "printed_page": "14",
      "source": "pdfjs_text_layer"
    },
    {
      "bbox": {
        "height": 12,
        "page_height": 737.008,
        "page_width": 524.409,
        "unit": "pdf_point",
        "width": 111.958,
        "x": 58.125,
        "y": 262.972
      },
      "evidence_role": "heading",
      "evidence_span_id": "tes_056cefe0b1d60032",
      "excerpt": "3. 你想创作一幅什么",
      "excerpt_hash": "781ddf4430f7796cb7ae14eb95fa1fb583b13a01f3cba060f26dcbced9791ddc",
      "node_id": "tcn_d27e18616546e508",
      "parser_version": "textbook-content-pdfjs-v3",
      "pdf_page": 21,
      "printed_page": "17",
      "source": "pdfjs_text_layer"
    },
    {
      "bbox": {
        "height": 12,
        "page_height": 737.008,
        "page_width": 524.409,
        "unit": "pdf_point",
        "width": 111.958,
        "x": 58.125,
        "y": 334.972
      },
      "evidence_role": "heading",
      "evidence_span_id": "tes_217e2444383d36e3",
      "excerpt": "1. 表现飞天动势的线",
      "excerpt_hash": "ab712805f631db0ea585d7900c1026d566aec8222732cdf484ac35fd079d8db4",
      "node_id": "tcn_1f5f24d814eb13c4",
      "parser_version": "textbook-content-pdfjs-v3",
      "pdf_page": 21,
      "printed_page": "17",
      "source": "pdfjs_text_layer"
    },
    {
      "bbox": {
        "height": 12,
        "page_height": 737.008,
        "page_width": 524.409,
        "unit": "pdf_point",
        "width": 111.958,
        "x": 58.125,
        "y": 298.972
      },
      "evidence_role": "heading",
      "evidence_span_id": "tes_9ef6bfc4581d14b7",
      "excerpt": "2. 飘带与人物的动势",
      "excerpt_hash": "9277958a2e89cee406820c0fe3747a11f5dc1201676d7c1f8358da7e23f3e615",
      "node_id": "tcn_d35f3405b772f944",
      "parser_version": "textbook-content-pdfjs-v3",
      "pdf_page": 21,
      "printed_page": "17",
      "source": "pdfjs_text_layer"
    },
    {
      "bbox": {
        "height": 12,
        "page_height": 737.008,
        "page_width": 524.409,
        "unit": "pdf_point",
        "width": 145.979,
        "x": 324.107,
        "y": 304.511
      },
      "evidence_role": "exercise",
      "evidence_span_id": "tes_466841752152586e",
      "excerpt": "根据对生活中笔的观察,了解笔的每个部分的功能,并且自己设计一支新颖实用的笔。",
      "excerpt_hash": "95fe1b6e81d95a580a3ea17590af3cbb53e77971b04b19d19e7d0c35a92d79b7",
      "node_id": "tcn_a1d8c57771367374",
      "parser_version": "textbook-content-pdfjs-v3",
      "pdf_page": 23,
      "printed_page": "19",
      "source": "pdfjs_text_layer"
    },
    {
      "bbox": {
        "height": 12,
        "page_height": 737.008,
        "page_width": 524.409,
        "unit": "pdf_point",
        "width": 94.954,
        "x": 235.759,
        "y": 317.084
      },
      "evidence_role": "heading",
      "evidence_span_id": "tes_2468eaa68eb48bac",
      "excerpt": "1. 用什么样的线",
      "excerpt_hash": "eed1e0ecb0d855ac99faea7c53b2a809ed066c4e4e3e096e49fc85165385a2de",
      "node_id": "tcn_8c57fc97c141b961",
      "parser_version": "textbook-content-pdfjs-v3",
      "pdf_page": 26,
      "printed_page": "22",
      "source": "pdfjs_text_layer"
    },
    {
      "bbox": {
        "height": 12,
        "page_height": 737.008,
        "page_width": 524.409,
        "unit": "pdf_point",
        "width": 94.954,
        "x": 235.759,
        "y": 263.084
      },
      "evidence_role": "heading",
      "evidence_span_id": "tes_a0c17a1b79175ccf",
      "excerpt": "2. 你认为本课中",
      "excerpt_hash": "d3a195fcf9c7acd783a4cd1acf502d5a76599c6f4ecbc0e46314b4d1df22dcf2",
      "node_id": "tcn_5914696396491ff1",
      "parser_version": "textbook-content-pdfjs-v3",
      "pdf_page": 26,
      "printed_page": "22",
      "source": "pdfjs_text_layer"
    },
    {
      "bbox": {
        "height": 12,
        "page_height": 737.008,
        "page_width": 524.409,
        "unit": "pdf_point",
        "width": 75.816,
        "x": 273.525,
        "y": 78.019
      },
      "evidence_role": "heading",
      "evidence_span_id": "tes_0fffb18ba0dacda1",
      "excerpt": "2. 这些形象有",
      "excerpt_hash": "69ec37dc12593093122cb433a7443984b3f5fc163e92631dfe333bd6b660e784",
      "node_id": "tcn_bf883430b056af76",
      "parser_version": "textbook-content-pdfjs-v3",
      "pdf_page": 28,
      "printed_page": "24",
      "source": "pdfjs_text_layer"
    },
    {
      "bbox": {
        "height": 12,
        "page_height": 737.008,
        "page_width": 524.409,
        "unit": "pdf_point",
        "width": 98.88,
        "x": 224.291,
        "y": 344.086
      },
      "evidence_role": "exercise",
      "evidence_span_id": "tes_89e92c5152da64ca",
      "excerpt": "结合,为自己设计一个美观的靠垫。",
      "excerpt_hash": "fbc22b7d578a7582fe188f20ed639280d6a12140fc508bb614a8c6059c8d5e57",
      "node_id": "tcn_2f51e90600be61aa",
      "parser_version": "textbook-content-pdfjs-v3",
      "pdf_page": 32,
      "printed_page": "28",
      "source": "pdfjs_text_layer"
    },
    {
      "bbox": {
        "height": 12,
        "page_height": 737.008,
        "page_width": 524.409,
        "unit": "pdf_point",
        "width": 113.35,
        "x": 390.478,
        "y": 416.433
      },
      "evidence_role": "heading",
      "evidence_span_id": "tes_1af1ec587725a688",
      "excerpt": "2. 伞的各部分应该如",
      "excerpt_hash": "71fc206c5b0c1ccab7b0ea758f357e3215dd5889220fea67c4ff05053c0318b0",
      "node_id": "tcn_593364283d74696d",
      "parser_version": "textbook-content-pdfjs-v3",
      "pdf_page": 34,
      "printed_page": "30",
      "source": "pdfjs_text_layer"
    },
    {
      "bbox": {
        "height": 12,
        "page_height": 737.008,
        "page_width": 524.409,
        "unit": "pdf_point",
        "width": 97.176,
        "x": 173.769,
        "y": 446.086
      },
      "evidence_role": "exercise",
      "evidence_span_id": "tes_8ca0fd8777aaf811",
      "excerpt": "设计并制作一只漂亮的小降落伞。做好后,拿到外面试一试,看看",
      "excerpt_hash": "95fbb64c26c88e3fccaa9b62e9b642e6860913ee006f680f23522c12023a27ed",
      "node_id": "tcn_9d7d71990f0c0e44",
      "parser_version": "textbook-content-pdfjs-v3",
      "pdf_page": 35,
      "printed_page": "31",
      "source": "pdfjs_text_layer"
    },
    {
      "bbox": {
        "height": 12,
        "page_height": 737.008,
        "page_width": 524.409,
        "unit": "pdf_point",
        "width": 112.826,
        "x": 223.659,
        "y": 332.606
      },
      "evidence_role": "heading",
      "evidence_span_id": "tes_5490f544593ce181",
      "excerpt": "2. 你认为学生作品中",
      "excerpt_hash": "060728c2accc4189a4437fd8d29415cce88c8248dcf3102342802ea5eb8d0b53",
      "node_id": "tcn_51fb739856bdb173",
      "parser_version": "textbook-content-pdfjs-v3",
      "pdf_page": 37,
      "printed_page": "33",
      "source": "pdfjs_text_layer"
    },
    {
      "bbox": {
        "height": 15.006,
        "page_height": 737.008,
        "page_width": 524.409,
        "unit": "pdf_point",
        "width": 265.356,
        "x": 141.006,
        "y": 194.44
      },
      "evidence_role": "heading",
      "evidence_span_id": "tes_15867ddbf39ac78f",
      "excerpt": "2 上色",
      "excerpt_hash": "c0f82db40d2428471cefa89dfa20d3f64e6d20611b78583c7c87aebb787ec7aa",
      "node_id": "tcn_72ee9bdeec7f5309",
      "parser_version": "textbook-content-pdfjs-v3",
      "pdf_page": 40,
      "printed_page": "36",
      "source": "pdfjs_text_layer"
    },
    {
      "bbox": {
        "height": 12,
        "page_height": 737.008,
        "page_width": 524.409,
        "unit": "pdf_point",
        "width": 106.276,
        "x": 60.383,
        "y": 560.511
      },
      "evidence_role": "heading",
      "evidence_span_id": "tes_2d73dd717e6e5e89",
      "excerpt": "1. 生活中的哪些材",
      "excerpt_hash": "9e2d5d22279427be32402e6dc3715dbf67447fcd3a661c233c069a9bdddaf5f9",
      "node_id": "tcn_54bfdf7c5aaf5e77",
      "parser_version": "textbook-content-pdfjs-v3",
      "pdf_page": 40,
      "printed_page": "36",
      "source": "pdfjs_text_layer"
    },
    {
      "bbox": {
        "height": 12,
        "page_height": 737.008,
        "page_width": 524.409,
        "unit": "pdf_point",
        "width": 106.276,
        "x": 60.383,
        "y": 452.511
      },
      "evidence_role": "heading",
      "evidence_span_id": "tes_8656de4512ee6f0a",
      "excerpt": "3. 刻字时有什么小",
      "excerpt_hash": "7e97fd8c157f5df663a38f3522278217307c373a6f1c3e02d4e80545e264f63e",
      "node_id": "tcn_57575faabac63e4f",
      "parser_version": "textbook-content-pdfjs-v3",
      "pdf_page": 40,
      "printed_page": "36",
      "source": "pdfjs_text_layer"
    },
    {
      "bbox": {
        "height": 12,
        "page_height": 737.008,
        "page_width": 524.409,
        "unit": "pdf_point",
        "width": 106.276,
        "x": 60.383,
        "y": 524.511
      },
      "evidence_role": "heading",
      "evidence_span_id": "tes_adaff8679f1afebd",
      "excerpt": "2. 本课刻印方法中",
      "excerpt_hash": "757a68dc50d5fc8a4fd69ced58b353b1b62152676fbcbd52a8eb61bf308da7c7",
      "node_id": "tcn_209b69e3934ef7c7",
      "parser_version": "textbook-content-pdfjs-v3",
      "pdf_page": 40,
      "printed_page": "36",
      "source": "pdfjs_text_layer"
    },
    {
      "bbox": {
        "height": 12,
        "page_height": 737.008,
        "page_width": 524.409,
        "unit": "pdf_point",
        "width": 100.968,
        "x": 174.108,
        "y": 499.5
      },
      "evidence_role": "exercise",
      "evidence_span_id": "tes_16b4ded7a3949a3c",
      "excerpt": "选择适合的材料、图 案、 文 字, 用 刻 印书签",
      "excerpt_hash": "bb90f0670aae03941c578b55bc809801bdf42768e4fce5ffaa790be80f507488",
      "node_id": "tcn_d2e54e4a05defe84",
      "parser_version": "textbook-content-pdfjs-v3",
      "pdf_page": 41,
      "printed_page": "37",
      "source": "pdfjs_text_layer"
    },
    {
      "bbox": {
        "height": 12,
        "page_height": 737.008,
        "page_width": 524.409,
        "unit": "pdf_point",
        "width": 151.92,
        "x": 353.628,
        "y": 109.834
      },
      "evidence_role": "heading",
      "evidence_span_id": "tes_3026308154f8b7da",
      "excerpt": "3. 你想如何表现你的现在和",
      "excerpt_hash": "8c00188de2df31e0f40bfd99e81090e85527a6e7325f8d3df5f46f13adb2e8db",
      "node_id": "tcn_2cc3659af38b7967",
      "parser_version": "textbook-content-pdfjs-v3",
      "pdf_page": 42,
      "printed_page": "38",
      "source": "pdfjs_text_layer"
    },
    {
      "bbox": {
        "height": 12,
        "page_height": 737.008,
        "page_width": 524.409,
        "unit": "pdf_point",
        "width": 151.92,
        "x": 353.628,
        "y": 163.834
      },
      "evidence_role": "heading",
      "evidence_span_id": "tes_60335b9622d1727a",
      "excerpt": "2. 同学们的作品采用了什么",
      "excerpt_hash": "b64f8fef6342728d12d1d7853caac100aba0df64027908ff2d644240be2e5754",
      "node_id": "tcn_06c114510f8bd743",
      "parser_version": "textbook-content-pdfjs-v3",
      "pdf_page": 42,
      "printed_page": "38",
      "source": "pdfjs_text_layer"
    },
    {
      "bbox": {
        "height": 12,
        "page_height": 737.008,
        "page_width": 524.409,
        "unit": "pdf_point",
        "width": 176.034,
        "x": 329.528,
        "y": 217.834
      },
      "evidence_role": "exercise",
      "evidence_span_id": "tes_782a3961847cf27f",
      "excerpt": "想一想,这两幅作品与我们之前见到的作品有什么不同?说一说,创作方法各有什么特点?",
      "excerpt_hash": "210d0b40445ceb86ba06b0415a11fef6e884048616d954994ce5c60ca7e0fbb7",
      "node_id": "tcn_5a0878f9e8867e0e",
      "parser_version": "textbook-content-pdfjs-v3",
      "pdf_page": 42,
      "printed_page": "38",
      "source": "pdfjs_text_layer"
    },
    {
      "bbox": {
        "height": 12,
        "page_height": 737.008,
        "page_width": 524.409,
        "unit": "pdf_point",
        "width": 156,
        "x": 238.11,
        "y": 358.834
      },
      "evidence_role": "exercise",
      "evidence_span_id": "tes_e170be7b8fbe563e",
      "excerpt": "把它画出来并附上说明文字。",
      "excerpt_hash": "eefa9a94fc824d23bf12cd85e8f37cc9478f1827bfcd9f470b8d897ef95f64bc",
      "node_id": "tcn_4ec45c5c7b5ae5ea",
      "parser_version": "textbook-content-pdfjs-v3",
      "pdf_page": 43,
      "printed_page": "39",
      "source": "pdfjs_text_layer"
    },
    {
      "bbox": {
        "height": 12,
        "page_height": 737.008,
        "page_width": 524.409,
        "unit": "pdf_point",
        "width": 88.638,
        "x": 377.013,
        "y": 73.59
      },
      "evidence_role": "heading",
      "evidence_span_id": "tes_1c44cb9891e14a56",
      "excerpt": "3. 学生作品中的",
      "excerpt_hash": "61e9b9aec450c3addd1a945d9a8c21c8262ea4bf7c022ff1171a7d94af6ccc76",
      "node_id": "tcn_5a2d3cae7e8523e2",
      "parser_version": "textbook-content-pdfjs-v3",
      "pdf_page": 44,
      "printed_page": "40",
      "source": "pdfjs_text_layer"
    },
    {
      "bbox": {
        "height": 12,
        "page_height": 737.008,
        "page_width": 524.409,
        "unit": "pdf_point",
        "width": 108.476,
        "x": 44.333,
        "y": 249.31
      },
      "evidence_role": "exercise",
      "evidence_span_id": "tes_063901b0147a1683",
      "excerpt": "制作一艘能浮在水面上的新颖美观的船,做好后和大家一起将船放到水",
      "excerpt_hash": "1d676b3bddaed35cab16a319a839cf4930ee98a4a186f388170891477f1519ea",
      "node_id": "tcn_1144700c92fdc4ab",
      "parser_version": "textbook-content-pdfjs-v3",
      "pdf_page": 45,
      "printed_page": "41",
      "source": "pdfjs_text_layer"
    },
    {
      "bbox": {
        "height": 12.505,
        "page_height": 737.008,
        "page_width": 524.409,
        "unit": "pdf_point",
        "width": 147.816,
        "x": 27.884,
        "y": 29.382
      },
      "evidence_role": "heading",
      "evidence_span_id": "tes_99de0dda1f55e726",
      "excerpt": "42 老相机",
      "excerpt_hash": "389823ff1557d70684004a2c5dfc3b3a783262dffe71cc37a70a319e07c7173f",
      "node_id": "tcn_13f7912fe04b874b",
      "parser_version": "textbook-content-pdfjs-v3",
      "pdf_page": 46,
      "printed_page": "42",
      "source": "pdfjs_text_layer"
    },
    {
      "bbox": {
        "height": 12,
        "page_height": 737.008,
        "page_width": 524.409,
        "unit": "pdf_point",
        "width": 189.679,
        "x": 62.552,
        "y": 367.204
      },
      "evidence_role": "heading",
      "evidence_span_id": "tes_f826759249783721",
      "excerpt": "3. 你想如何拍一张主题明确的人像",
      "excerpt_hash": "2de743291caa6bf1719ff6492fa2117843240b820f09152b736205f76f7df3fa",
      "node_id": "tcn_38fe5976c40b3927",
      "parser_version": "textbook-content-pdfjs-v3",
      "pdf_page": 47,
      "printed_page": "43",
      "source": "pdfjs_text_layer"
    },
    {
      "bbox": {
        "height": 12,
        "page_height": 737.008,
        "page_width": 524.409,
        "unit": "pdf_point",
        "width": 100.649,
        "x": 45.36,
        "y": 558.467
      },
      "evidence_role": "heading",
      "evidence_span_id": "tes_49484d55cbf6d50b",
      "excerpt": "3. 你想剪刻一个什",
      "excerpt_hash": "02023f382c069f77c60e4e62172aac856394e265f41edfa59a80d54624f52938",
      "node_id": "tcn_8007861f625915be",
      "parser_version": "textbook-content-pdfjs-v3",
      "pdf_page": 49,
      "printed_page": "45",
      "source": "pdfjs_text_layer"
    },
    {
      "bbox": {
        "height": 12,
        "page_height": 737.008,
        "page_width": 524.409,
        "unit": "pdf_point",
        "width": 116.256,
        "x": 362.844,
        "y": 353.633
      },
      "evidence_role": "exercise",
      "evidence_span_id": "tes_adf59d04daab690b",
      "excerpt": "设计制作一个有美好寓意的剪纸作品。",
      "excerpt_hash": "5ca38b14a36bb795824f94adc6b569b0d6f919c8e635d6cc0aa255bfc5513efb",
      "node_id": "tcn_ebe241df05664c1c",
      "parser_version": "textbook-content-pdfjs-v3",
      "pdf_page": 49,
      "printed_page": "45",
      "source": "pdfjs_text_layer"
    },
    {
      "bbox": {
        "height": 12,
        "page_height": 737.008,
        "page_width": 524.409,
        "unit": "pdf_point",
        "width": 100.625,
        "x": 45.36,
        "y": 630.467
      },
      "evidence_role": "heading",
      "evidence_span_id": "tes_c426b0ab89acec2c",
      "excerpt": "1. 介绍自己了解的",
      "excerpt_hash": "0e223731c7933f0b02bc89e1f40ba279288a2dc629a152edd31a4bbe7290673e",
      "node_id": "tcn_505d22910172db5c",
      "parser_version": "textbook-content-pdfjs-v3",
      "pdf_page": 49,
      "printed_page": "45",
      "source": "pdfjs_text_layer"
    },
    {
      "bbox": {
        "height": 13.349,
        "page_height": 737.008,
        "page_width": 524.409,
        "unit": "pdf_point",
        "width": 302.872,
        "x": 66.64,
        "y": 179.603
      },
      "evidence_role": "heading",
      "evidence_span_id": "tes_a0fb9f3b509f83b5",
      "excerpt": "2. 你觉得哪 笔筒",
      "excerpt_hash": "5e8be368572bd0d26b6566809d8f66a0cd4e900bd7b84e91cc9be561a3749b9e",
      "node_id": "tcn_9e0506bc55a540f4",
      "parser_version": "textbook-content-pdfjs-v3",
      "pdf_page": 50,
      "printed_page": "46",
      "source": "pdfjs_text_layer"
    }
  ],
  "extraction": {
    "average_characters_per_page": 198.2,
    "extracted_at": "2026-07-17T09:42:14.165878Z",
    "notes": [
      "数字印刷页与 PDF 页偏移 4，由 40 页重复证据支持。",
      "只有在正文页面直接回查到的标题才自动进入已核对目录。"
    ],
    "page_count_checked": 50,
    "pages_with_text": 49
  },
  "file_size_bytes": 8041134,
  "generated_at": "2026-07-17T05:13:38.674Z",
  "grade": 4,
  "grade_label": "4年级",
  "machine_checked_alignment_count": 0,
  "page_count": 50,
  "page_map": [
    {
      "confidence": 0.99,
      "label": "印刷页 1",
      "pdf_page": 5,
      "printed_page": "1",
      "review_status": "approved"
    },
    {
      "confidence": 0.99,
      "label": "印刷页 2",
      "pdf_page": 6,
      "printed_page": "2",
      "review_status": "approved"
    },
    {
      "confidence": 0.99,
      "label": "印刷页 3",
      "pdf_page": 7,
      "printed_page": "3",
      "review_status": "approved"
    },
    {
      "confidence": 0.99,
      "label": "印刷页 4",
      "pdf_page": 8,
      "printed_page": "4",
      "review_status": "approved"
    },
    {
      "confidence": 0.99,
      "label": "印刷页 5",
      "pdf_page": 9,
      "printed_page": "5",
      "review_status": "approved"
    },
    {
      "confidence": 0.99,
      "label": "印刷页 6",
      "pdf_page": 10,
      "printed_page": "6",
      "review_status": "approved"
    },
    {
      "confidence": 0.99,
      "label": "印刷页 7",
      "pdf_page": 11,
      "printed_page": "7",
      "review_status": "approved"
    },
    {
      "confidence": 0.99,
      "label": "印刷页 8",
      "pdf_page": 12,
      "printed_page": "8",
      "review_status": "approved"
    },
    {
      "confidence": 0.99,
      "label": "印刷页 9",
      "pdf_page": 13,
      "printed_page": "9",
      "review_status": "approved"
    },
    {
      "confidence": 0.99,
      "label": "印刷页 10",
      "pdf_page": 14,
      "printed_page": "10",
      "review_status": "approved"
    },
    {
      "confidence": 0.99,
      "label": "印刷页 11",
      "pdf_page": 15,
      "printed_page": "11",
      "review_status": "approved"
    },
    {
      "confidence": 0.99,
      "label": "印刷页 12",
      "pdf_page": 16,
      "printed_page": "12",
      "review_status": "approved"
    },
    {
      "confidence": 0.99,
      "label": "印刷页 13",
      "pdf_page": 17,
      "printed_page": "13",
      "review_status": "approved"
    },
    {
      "confidence": 0.99,
      "label": "印刷页 14",
      "pdf_page": 18,
      "printed_page": "14",
      "review_status": "approved"
    },
    {
      "confidence": 0.99,
      "label": "印刷页 15",
      "pdf_page": 19,
      "printed_page": "15",
      "review_status": "approved"
    },
    {
      "confidence": 0.99,
      "label": "印刷页 16",
      "pdf_page": 20,
      "printed_page": "16",
      "review_status": "approved"
    },
    {
      "confidence": 0.99,
      "label": "印刷页 17",
      "pdf_page": 21,
      "printed_page": "17",
      "review_status": "approved"
    },
    {
      "confidence": 0.99,
      "label": "印刷页 18",
      "pdf_page": 22,
      "printed_page": "18",
      "review_status": "approved"
    },
    {
      "confidence": 0.99,
      "label": "印刷页 19",
      "pdf_page": 23,
      "printed_page": "19",
      "review_status": "approved"
    },
    {
      "confidence": 0.99,
      "label": "印刷页 20",
      "pdf_page": 24,
      "printed_page": "20",
      "review_status": "approved"
    },
    {
      "confidence": 0.99,
      "label": "印刷页 21",
      "pdf_page": 25,
      "printed_page": "21",
      "review_status": "approved"
    },
    {
      "confidence": 0.99,
      "label": "印刷页 22",
      "pdf_page": 26,
      "printed_page": "22",
      "review_status": "approved"
    },
    {
      "confidence": 0.99,
      "label": "印刷页 23",
      "pdf_page": 27,
      "printed_page": "23",
      "review_status": "approved"
    },
    {
      "confidence": 0.99,
      "label": "印刷页 24",
      "pdf_page": 28,
      "printed_page": "24",
      "review_status": "approved"
    },
    {
      "confidence": 0.99,
      "label": "印刷页 25",
      "pdf_page": 29,
      "printed_page": "25",
      "review_status": "approved"
    },
    {
      "confidence": 0.99,
      "label": "印刷页 26",
      "pdf_page": 30,
      "printed_page": "26",
      "review_status": "approved"
    },
    {
      "confidence": 0.99,
      "label": "印刷页 27",
      "pdf_page": 31,
      "printed_page": "27",
      "review_status": "approved"
    },
    {
      "confidence": 0.99,
      "label": "印刷页 28",
      "pdf_page": 32,
      "printed_page": "28",
      "review_status": "approved"
    },
    {
      "confidence": 0.99,
      "label": "印刷页 29",
      "pdf_page": 33,
      "printed_page": "29",
      "review_status": "approved"
    },
    {
      "confidence": 0.99,
      "label": "印刷页 30",
      "pdf_page": 34,
      "printed_page": "30",
      "review_status": "approved"
    },
    {
      "confidence": 0.99,
      "label": "印刷页 31",
      "pdf_page": 35,
      "printed_page": "31",
      "review_status": "approved"
    },
    {
      "confidence": 0.99,
      "label": "印刷页 32",
      "pdf_page": 36,
      "printed_page": "32",
      "review_status": "approved"
    },
    {
      "confidence": 0.99,
      "label": "印刷页 33",
      "pdf_page": 37,
      "printed_page": "33",
      "review_status": "approved"
    },
    {
      "confidence": 0.99,
      "label": "印刷页 34",
      "pdf_page": 38,
      "printed_page": "34",
      "review_status": "approved"
    },
    {
      "confidence": 0.99,
      "label": "印刷页 35",
      "pdf_page": 39,
      "printed_page": "35",
      "review_status": "approved"
    },
    {
      "confidence": 0.99,
      "label": "印刷页 36",
      "pdf_page": 40,
      "printed_page": "36",
      "review_status": "approved"
    },
    {
      "confidence": 0.99,
      "label": "印刷页 37",
      "pdf_page": 41,
      "printed_page": "37",
      "review_status": "approved"
    },
    {
      "confidence": 0.99,
      "label": "印刷页 38",
      "pdf_page": 42,
      "printed_page": "38",
      "review_status": "approved"
    },
    {
      "confidence": 0.99,
      "label": "印刷页 39",
      "pdf_page": 43,
      "printed_page": "39",
      "review_status": "approved"
    },
    {
      "confidence": 0.99,
      "label": "印刷页 40",
      "pdf_page": 44,
      "printed_page": "40",
      "review_status": "approved"
    },
    {
      "confidence": 0.99,
      "label": "印刷页 41",
      "pdf_page": 45,
      "printed_page": "41",
      "review_status": "approved"
    },
    {
      "confidence": 0.99,
      "label": "印刷页 42",
      "pdf_page": 46,
      "printed_page": "42",
      "review_status": "approved"
    },
    {
      "confidence": 0.99,
      "label": "印刷页 43",
      "pdf_page": 47,
      "printed_page": "43",
      "review_status": "approved"
    },
    {
      "confidence": 0.99,
      "label": "印刷页 44",
      "pdf_page": 48,
      "printed_page": "44",
      "review_status": "approved"
    },
    {
      "confidence": 0.99,
      "label": "印刷页 45",
      "pdf_page": 49,
      "printed_page": "45",
      "review_status": "approved"
    },
    {
      "confidence": 0.99,
      "label": "印刷页 46",
      "pdf_page": 50,
      "printed_page": "46",
      "review_status": "approved"
    }
  ],
  "page_map_status": "approved",
  "published_alignment_count": 0,
  "reading_available": true,
  "related_resource_count": 0,
  "related_resources": [],
  "relation_status": "machine_checked",
  "resource_type": "student_textbook",
  "revision_label": "版次待核实",
  "revision_status": "revision_unknown",
  "short_title": "美术 4年级 上册",
  "stage": "primary",
  "stage_label": "小学",
  "standard_scope_count": 46,
  "standard_scopes": [
    {
      "algorithm_version": "full-alignment-scope-preserve-v2",
      "edition_id": "ed_26d72869b7188e2196d2",
      "evidence_role": "discipline_textbook",
      "grade_band": "H2",
      "relation_type": "curriculum_scope",
      "review_status": "machine_checked",
      "scope_id": "tcs_fbf879fc86b8f9dd",
      "standard_codes": [
        "AR-D2-AA-001",
        "AR-D2-AA-002",
        "AR-D2-AA-009",
        "AR-D2-AA-022",
        "AR-D2-AA-025",
        "AR-D2-AA-026",
        "AR-D2-AE-001",
        "AR-D2-AE-002",
        "AR-D2-AE-003",
        "AR-D2-AE-004",
        "AR-D2-AE-005",
        "AR-D2-AE-006",
        "AR-D2-AE-007",
        "AR-D2-AE-008",
        "AR-D2-AE-009",
        "AR-D2-AE-010",
        "AR-D2-AE-011",
        "AR-D2-AE-012",
        "AR-D2-AE-013",
        "AR-D2-AE-014",
        "AR-D2-AE-015",
        "AR-D2-AE-016",
        "AR-D2-AE-017",
        "AR-D2-AE-018",
        "AR-D2-AE-019",
        "AR-D2-AE-020",
        "AR-D2-AE-021",
        "AR-D2-AE-023",
        "AR-D2-AE-024",
        "AR-D2-CP-010",
        "AR-D2-CP-011",
        "AR-D2-CP-012",
        "AR-D2-CP-013",
        "AR-D2-CP-014",
        "AR-D2-CP-016",
        "AR-D2-CP-017",
        "AR-D2-CP-019",
        "AR-D2-CP-020",
        "AR-D2-CU-001",
        "AR-D2-CU-002",
        "AR-D2-CU-003",
        "AR-D2-CU-004",
        "AR-D2-CU-005",
        "AR-D2-CU-006",
        "AR-D2-CU-007",
        "AR-D2-CU-008"
      ],
      "standard_subject_slug": "arts"
    }
  ],
  "subject": "美术",
  "subject_slug": "art",
  "text_quality": "native_text",
  "title": "美术4年级上册",
  "toc": [
    {
      "confidence": 0.92,
      "end_pdf_page": 50,
      "entry_id": "tcu_7cedb850b44b47c9",
      "kind": "section",
      "level": 2,
      "parent_id": null,
      "pdf_page": 4,
      "printed_page": null,
      "review_status": "approved",
      "source": "heading_match",
      "title": "403.34 平方米,画面高 4.26 米,全长 94.68 米,共画天神 286 身,描绘了"
    }
  ],
  "toc_entry_count": 1,
  "toc_status": "approved",
  "unit_count": 0,
  "volume": "上册",
  "work_id": "work_26d72869b7188e21"
}
