{
  "edition_id": "ed_006d5ed61c055eb63857",
  "generated_at": "2026-07-17T05:13:38.674Z",
  "pages": {
    "1": {
      "alignment_ids": [],
      "evidence_span_ids": [],
      "node_ids": [
        "tcn_5ef803caed52f97b"
      ]
    },
    "2": {
      "alignment_ids": [],
      "evidence_span_ids": [],
      "node_ids": [
        "tcn_bc21b90c2069a622"
      ]
    },
    "3": {
      "alignment_ids": [],
      "evidence_span_ids": [],
      "node_ids": [
        "tcn_f434dc795569bbc7"
      ]
    },
    "4": {
      "alignment_ids": [],
      "evidence_span_ids": [],
      "node_ids": [
        "tcn_20dbefb22bd7e52e"
      ]
    },
    "6": {
      "alignment_ids": [],
      "evidence_span_ids": [],
      "node_ids": [
        "tcn_a77f890044921dce"
      ]
    },
    "7": {
      "alignment_ids": [],
      "evidence_span_ids": [],
      "node_ids": [
        "tcn_a9b577bffae543cc"
      ]
    },
    "8": {
      "alignment_ids": [],
      "evidence_span_ids": [],
      "node_ids": [
        "tcn_f9430343d539164f"
      ]
    },
    "9": {
      "alignment_ids": [],
      "evidence_span_ids": [
        "tes_810c510086807639"
      ],
      "node_ids": [
        "tcn_26f229d32d9b295a",
        "tcn_4ab50aca40eb662a",
        "tcn_4cd52f1e616ad84f"
      ]
    },
    "10": {
      "alignment_ids": [],
      "evidence_span_ids": [
        "tes_1917bfc6c26024f7",
        "tes_704db15c488523a6",
        "tes_7ad8f0200704dc02"
      ],
      "node_ids": [
        "tcn_06d00a68b58c3118",
        "tcn_313e050ee1564e67",
        "tcn_4cd52f1e616ad84f",
        "tcn_4fc7aca85a7fd308",
        "tcn_b834f5d0b258ec2e"
      ]
    },
    "11": {
      "alignment_ids": [],
      "evidence_span_ids": [
        "tes_0141ca689691a95f"
      ],
      "node_ids": [
        "tcn_0e1a1bd6211611ad",
        "tcn_4cd52f1e616ad84f",
        "tcn_60a31b171f66b0cf"
      ]
    },
    "12": {
      "alignment_ids": [],
      "evidence_span_ids": [
        "tes_20c5e9fe8e749c77"
      ],
      "node_ids": [
        "tcn_3897b9863f043424",
        "tcn_4cd52f1e616ad84f",
        "tcn_52b791f9f7a123a6"
      ]
    },
    "13": {
      "alignment_ids": [
        "tca_cb8ab3566f28732a"
      ],
      "evidence_span_ids": [
        "tes_cf4b35d23569909f"
      ],
      "node_ids": [
        "tcn_2385e1a30eeb604f",
        "tcn_54dfb6b1e6881ecd",
        "tcn_7d718a10136eb033"
      ]
    },
    "14": {
      "alignment_ids": [],
      "evidence_span_ids": [
        "tes_0ba2d6295de92d9c",
        "tes_0edb002d166d7f2c",
        "tes_16067d75fbef9183",
        "tes_42e0783f89c1ea07"
      ],
      "node_ids": [
        "tcn_05ef2bfdc972f129",
        "tcn_65ecbab64a6a5764",
        "tcn_7d718a10136eb033",
        "tcn_8e3d41c266debc92",
        "tcn_977029fc42794ffd",
        "tcn_abbc9e3f01a0dd8e"
      ]
    },
    "15": {
      "alignment_ids": [],
      "evidence_span_ids": [],
      "node_ids": [
        "tcn_16e5d78d4451c338",
        "tcn_7d718a10136eb033",
        "tcn_977029fc42794ffd"
      ]
    },
    "16": {
      "alignment_ids": [],
      "evidence_span_ids": [
        "tes_345bf8ff4838a2a8"
      ],
      "node_ids": [
        "tcn_7d718a10136eb033",
        "tcn_bee6e97279135cab",
        "tcn_e6086080e207ece9"
      ]
    },
    "17": {
      "alignment_ids": [],
      "evidence_span_ids": [],
      "node_ids": [
        "tcn_7d718a10136eb033",
        "tcn_af11830a401b6f97",
        "tcn_bee6e97279135cab"
      ]
    },
    "18": {
      "alignment_ids": [],
      "evidence_span_ids": [
        "tes_5e67feb1fa07cf7a"
      ],
      "node_ids": [
        "tcn_7d718a10136eb033",
        "tcn_d96a4f0696f084f4",
        "tcn_f917e5022baefb49"
      ]
    },
    "19": {
      "alignment_ids": [],
      "evidence_span_ids": [],
      "node_ids": [
        "tcn_76cd95a96a31c959",
        "tcn_7d718a10136eb033",
        "tcn_f917e5022baefb49"
      ]
    },
    "20": {
      "alignment_ids": [],
      "evidence_span_ids": [],
      "node_ids": [
        "tcn_7d718a10136eb033",
        "tcn_f917e5022baefb49",
        "tcn_f9e3df2a9ca711e3"
      ]
    },
    "21": {
      "alignment_ids": [],
      "evidence_span_ids": [
        "tes_dd7682bb1b569b18"
      ],
      "node_ids": [
        "tcn_7d718a10136eb033",
        "tcn_8e2caac5bcfd9a26",
        "tcn_95c1e1943350946d"
      ]
    },
    "22": {
      "alignment_ids": [],
      "evidence_span_ids": [],
      "node_ids": [
        "tcn_7d718a10136eb033",
        "tcn_8e2caac5bcfd9a26",
        "tcn_c2781a8fa68ef919"
      ]
    },
    "23": {
      "alignment_ids": [
        "tca_08cfe8b9e886fea1",
        "tca_670e83617c35e552"
      ],
      "evidence_span_ids": [
        "tes_4234d7fc53dcef5a",
        "tes_c806750b1d785c2f"
      ],
      "node_ids": [
        "tcn_2c9cf533b31c46fd",
        "tcn_43e324b8aab86fb7",
        "tcn_7d718a10136eb033",
        "tcn_856219f5ab5ffde5"
      ]
    },
    "24": {
      "alignment_ids": [
        "tca_670e83617c35e552"
      ],
      "evidence_span_ids": [
        "tes_4234d7fc53dcef5a"
      ],
      "node_ids": [
        "tcn_43e324b8aab86fb7",
        "tcn_7d718a10136eb033",
        "tcn_bce3b1ea45569d3d"
      ]
    },
    "25": {
      "alignment_ids": [
        "tca_670e83617c35e552"
      ],
      "evidence_span_ids": [
        "tes_4234d7fc53dcef5a"
      ],
      "node_ids": [
        "tcn_43e324b8aab86fb7",
        "tcn_7d718a10136eb033",
        "tcn_c1df458d313eec9c"
      ]
    },
    "26": {
      "alignment_ids": [
        "tca_670e83617c35e552"
      ],
      "evidence_span_ids": [
        "tes_4234d7fc53dcef5a"
      ],
      "node_ids": [
        "tcn_1f44146362f4f556",
        "tcn_43e324b8aab86fb7",
        "tcn_7d718a10136eb033"
      ]
    },
    "27": {
      "alignment_ids": [],
      "evidence_span_ids": [
        "tes_f3e95159ec86dd3f"
      ],
      "node_ids": [
        "tcn_34fbf6d2844b819c",
        "tcn_7d718a10136eb033",
        "tcn_d96691aaf656aacb"
      ]
    },
    "28": {
      "alignment_ids": [],
      "evidence_span_ids": [],
      "node_ids": [
        "tcn_886aa031591b452f",
        "tcn_ae3a836cc2a642b6"
      ]
    },
    "29": {
      "alignment_ids": [],
      "evidence_span_ids": [],
      "node_ids": [
        "tcn_75ac5b16ebf56087",
        "tcn_886aa031591b452f"
      ]
    },
    "30": {
      "alignment_ids": [],
      "evidence_span_ids": [],
      "node_ids": [
        "tcn_4f3e2f016e0af6dc",
        "tcn_886aa031591b452f"
      ]
    },
    "31": {
      "alignment_ids": [],
      "evidence_span_ids": [],
      "node_ids": [
        "tcn_886aa031591b452f",
        "tcn_b9a60ba44e194df2"
      ]
    },
    "32": {
      "alignment_ids": [],
      "evidence_span_ids": [],
      "node_ids": [
        "tcn_4e1f6650ff2a1ec0",
        "tcn_886aa031591b452f"
      ]
    },
    "33": {
      "alignment_ids": [],
      "evidence_span_ids": [],
      "node_ids": [
        "tcn_886aa031591b452f",
        "tcn_af878a27bbb4478f"
      ]
    },
    "34": {
      "alignment_ids": [],
      "evidence_span_ids": [],
      "node_ids": [
        "tcn_886aa031591b452f",
        "tcn_c18a35c35f99c177"
      ]
    },
    "35": {
      "alignment_ids": [
        "tca_59672d1ae2b67de3"
      ],
      "evidence_span_ids": [
        "tes_960833715a5e9a81",
        "tes_a117218f84195775",
        "tes_ffd527ac8beef5bb"
      ],
      "node_ids": [
        "tcn_10f8c896b9079c68",
        "tcn_1fb096a3e0514c66",
        "tcn_4b6dd74cc4f4c817",
        "tcn_a35c6a58663f7bea",
        "tcn_d4ec9beea58a88be"
      ]
    },
    "36": {
      "alignment_ids": [
        "tca_59672d1ae2b67de3"
      ],
      "evidence_span_ids": [
        "tes_a117218f84195775"
      ],
      "node_ids": [
        "tcn_1fb096a3e0514c66",
        "tcn_57b19e1dc028db52",
        "tcn_d4ec9beea58a88be"
      ]
    },
    "37": {
      "alignment_ids": [
        "tca_59672d1ae2b67de3"
      ],
      "evidence_span_ids": [
        "tes_a117218f84195775"
      ],
      "node_ids": [
        "tcn_1fb096a3e0514c66",
        "tcn_2f90a8f299d71230",
        "tcn_d4ec9beea58a88be"
      ]
    },
    "38": {
      "alignment_ids": [
        "tca_59672d1ae2b67de3"
      ],
      "evidence_span_ids": [
        "tes_a117218f84195775"
      ],
      "node_ids": [
        "tcn_1fb096a3e0514c66",
        "tcn_9f3e7b0bdfc1b771",
        "tcn_d4ec9beea58a88be"
      ]
    },
    "39": {
      "alignment_ids": [
        "tca_59672d1ae2b67de3"
      ],
      "evidence_span_ids": [
        "tes_a117218f84195775"
      ],
      "node_ids": [
        "tcn_1fb096a3e0514c66",
        "tcn_2b6e10526aa69c1a",
        "tcn_d4ec9beea58a88be"
      ]
    },
    "40": {
      "alignment_ids": [
        "tca_59672d1ae2b67de3"
      ],
      "evidence_span_ids": [
        "tes_a117218f84195775"
      ],
      "node_ids": [
        "tcn_1fb096a3e0514c66",
        "tcn_9f63425f8b2071c1",
        "tcn_d4ec9beea58a88be"
      ]
    },
    "41": {
      "alignment_ids": [],
      "evidence_span_ids": [],
      "node_ids": [
        "tcn_bda78802ce9dafd8",
        "tcn_d9f05d9367a39129"
      ]
    },
    "42": {
      "alignment_ids": [],
      "evidence_span_ids": [],
      "node_ids": [
        "tcn_3631b60933c966f1",
        "tcn_d9f05d9367a39129"
      ]
    },
    "43": {
      "alignment_ids": [],
      "evidence_span_ids": [],
      "node_ids": [
        "tcn_d9f05d9367a39129",
        "tcn_e14177ebdeb91248"
      ]
    },
    "44": {
      "alignment_ids": [],
      "evidence_span_ids": [
        "tes_f182337fda4f53e2"
      ],
      "node_ids": [
        "tcn_23e9183b73d42fa7",
        "tcn_41e96bbf8fb870e7",
        "tcn_d9f05d9367a39129"
      ]
    },
    "45": {
      "alignment_ids": [],
      "evidence_span_ids": [],
      "node_ids": [
        "tcn_ca5b9e9e96fc1274",
        "tcn_d9f05d9367a39129"
      ]
    },
    "46": {
      "alignment_ids": [],
      "evidence_span_ids": [],
      "node_ids": [
        "tcn_0e24d3410c684d17",
        "tcn_d9f05d9367a39129"
      ]
    },
    "47": {
      "alignment_ids": [],
      "evidence_span_ids": [],
      "node_ids": [
        "tcn_95573f8631c3ee6a",
        "tcn_d9f05d9367a39129"
      ]
    },
    "48": {
      "alignment_ids": [],
      "evidence_span_ids": [
        "tes_702295d11eb74426"
      ],
      "node_ids": [
        "tcn_44aa230dd2bf7d6d",
        "tcn_a660be64c051e74d",
        "tcn_dd50bbbd5d9c3529"
      ]
    },
    "49": {
      "alignment_ids": [],
      "evidence_span_ids": [],
      "node_ids": [
        "tcn_44aa230dd2bf7d6d",
        "tcn_dd50bbbd5d9c3529",
        "tcn_e876bbda4a5a4cfd"
      ]
    },
    "50": {
      "alignment_ids": [],
      "evidence_span_ids": [],
      "node_ids": [
        "tcn_44aa230dd2bf7d6d",
        "tcn_dd50bbbd5d9c3529",
        "tcn_df2600a649edf702"
      ]
    },
    "51": {
      "alignment_ids": [],
      "evidence_span_ids": [],
      "node_ids": [
        "tcn_943851bf4a059a75",
        "tcn_e1b91e454e969057"
      ]
    },
    "52": {
      "alignment_ids": [],
      "evidence_span_ids": [],
      "node_ids": [
        "tcn_02c3d6f6971419ef",
        "tcn_ab30c1f6ac245c05"
      ]
    },
    "53": {
      "alignment_ids": [],
      "evidence_span_ids": [
        "tes_51f2fec6c019865e"
      ],
      "node_ids": [
        "tcn_868c1efc146307f9",
        "tcn_ab30c1f6ac245c05",
        "tcn_ec7887bc7de0a05e"
      ]
    },
    "54": {
      "alignment_ids": [],
      "evidence_span_ids": [],
      "node_ids": [
        "tcn_714645f440c9ed2a",
        "tcn_ab30c1f6ac245c05",
        "tcn_ec7887bc7de0a05e"
      ]
    },
    "55": {
      "alignment_ids": [],
      "evidence_span_ids": [],
      "node_ids": [
        "tcn_ab30c1f6ac245c05",
        "tcn_c696f966824293be",
        "tcn_ec7887bc7de0a05e"
      ]
    },
    "56": {
      "alignment_ids": [],
      "evidence_span_ids": [],
      "node_ids": [
        "tcn_8a3e2e9065cd4c0f",
        "tcn_ab30c1f6ac245c05",
        "tcn_ec7887bc7de0a05e"
      ]
    },
    "57": {
      "alignment_ids": [],
      "evidence_span_ids": [],
      "node_ids": [
        "tcn_3c6728a5744ad993",
        "tcn_ab30c1f6ac245c05",
        "tcn_ec7887bc7de0a05e"
      ]
    },
    "58": {
      "alignment_ids": [],
      "evidence_span_ids": [],
      "node_ids": [
        "tcn_ab30c1f6ac245c05",
        "tcn_ec7887bc7de0a05e",
        "tcn_f39f10d00a14ad5d"
      ]
    },
    "59": {
      "alignment_ids": [],
      "evidence_span_ids": [],
      "node_ids": [
        "tcn_ab30c1f6ac245c05",
        "tcn_ae66fb5d04d1c827",
        "tcn_ec7887bc7de0a05e"
      ]
    },
    "60": {
      "alignment_ids": [],
      "evidence_span_ids": [],
      "node_ids": [
        "tcn_1fa1929cf4fa66ce",
        "tcn_e806dddff4877996"
      ]
    },
    "61": {
      "alignment_ids": [],
      "evidence_span_ids": [],
      "node_ids": [
        "tcn_1fa1929cf4fa66ce",
        "tcn_9d55147b1a99553e",
        "tcn_e5dea10712e04d67"
      ]
    },
    "62": {
      "alignment_ids": [],
      "evidence_span_ids": [],
      "node_ids": [
        "tcn_1fa1929cf4fa66ce",
        "tcn_a921a6f66ebfd284",
        "tcn_e5dea10712e04d67"
      ]
    },
    "63": {
      "alignment_ids": [],
      "evidence_span_ids": [],
      "node_ids": [
        "tcn_1fa1929cf4fa66ce",
        "tcn_24dfe614d4780471",
        "tcn_e5dea10712e04d67"
      ]
    },
    "64": {
      "alignment_ids": [],
      "evidence_span_ids": [],
      "node_ids": [
        "tcn_1fa1929cf4fa66ce",
        "tcn_c6426050ac904e01",
        "tcn_e5dea10712e04d67"
      ]
    },
    "65": {
      "alignment_ids": [],
      "evidence_span_ids": [],
      "node_ids": [
        "tcn_1fa1929cf4fa66ce",
        "tcn_a892fbae3eb54cf4",
        "tcn_e5dea10712e04d67"
      ]
    },
    "66": {
      "alignment_ids": [],
      "evidence_span_ids": [],
      "node_ids": [
        "tcn_1fa1929cf4fa66ce",
        "tcn_320e5f5e6e494500",
        "tcn_e5dea10712e04d67"
      ]
    },
    "67": {
      "alignment_ids": [],
      "evidence_span_ids": [
        "tes_8b301e0a61153e17"
      ],
      "node_ids": [
        "tcn_1fa1929cf4fa66ce",
        "tcn_515d721be39adebd",
        "tcn_9e9dc5fb724d4c54",
        "tcn_e5dea10712e04d67"
      ]
    },
    "68": {
      "alignment_ids": [],
      "evidence_span_ids": [],
      "node_ids": [
        "tcn_1fa1929cf4fa66ce",
        "tcn_515d721be39adebd",
        "tcn_e20f6b51cfa1f1ca",
        "tcn_e5dea10712e04d67"
      ]
    },
    "69": {
      "alignment_ids": [],
      "evidence_span_ids": [],
      "node_ids": [
        "tcn_1fa1929cf4fa66ce",
        "tcn_515d721be39adebd",
        "tcn_b5016353fbe6e3da",
        "tcn_ef92085b06e7f294"
      ]
    },
    "70": {
      "alignment_ids": [],
      "evidence_span_ids": [],
      "node_ids": [
        "tcn_1fa1929cf4fa66ce",
        "tcn_515d721be39adebd",
        "tcn_ae5ce188a843df62",
        "tcn_b5016353fbe6e3da"
      ]
    },
    "71": {
      "alignment_ids": [],
      "evidence_span_ids": [],
      "node_ids": [
        "tcn_1fa1929cf4fa66ce",
        "tcn_515d721be39adebd",
        "tcn_b5016353fbe6e3da",
        "tcn_d2d65dc13da8ae93"
      ]
    },
    "72": {
      "alignment_ids": [],
      "evidence_span_ids": [],
      "node_ids": [
        "tcn_1fa1929cf4fa66ce",
        "tcn_515d721be39adebd",
        "tcn_52d4fd9325a6e11d",
        "tcn_b5016353fbe6e3da"
      ]
    },
    "73": {
      "alignment_ids": [],
      "evidence_span_ids": [],
      "node_ids": [
        "tcn_067e771ea5e46218",
        "tcn_1fa1929cf4fa66ce",
        "tcn_515d721be39adebd",
        "tcn_b5016353fbe6e3da"
      ]
    },
    "74": {
      "alignment_ids": [],
      "evidence_span_ids": [],
      "node_ids": [
        "tcn_1fa1929cf4fa66ce",
        "tcn_515d721be39adebd",
        "tcn_b5016353fbe6e3da",
        "tcn_b8e355e1a5536e2b"
      ]
    },
    "75": {
      "alignment_ids": [],
      "evidence_span_ids": [],
      "node_ids": [
        "tcn_1fa1929cf4fa66ce",
        "tcn_515d721be39adebd",
        "tcn_ae624e1b191e3956",
        "tcn_b5016353fbe6e3da"
      ]
    },
    "76": {
      "alignment_ids": [],
      "evidence_span_ids": [],
      "node_ids": [
        "tcn_1fa1929cf4fa66ce",
        "tcn_515d721be39adebd",
        "tcn_b5016353fbe6e3da",
        "tcn_f707b2b212d32ef0"
      ]
    },
    "77": {
      "alignment_ids": [],
      "evidence_span_ids": [],
      "node_ids": [
        "tcn_1fa1929cf4fa66ce",
        "tcn_515d721be39adebd",
        "tcn_51985e653e45d305",
        "tcn_b5016353fbe6e3da"
      ]
    },
    "78": {
      "alignment_ids": [],
      "evidence_span_ids": [
        "tes_a7b459e5af30e36b"
      ],
      "node_ids": [
        "tcn_1fa1929cf4fa66ce",
        "tcn_b5016353fbe6e3da",
        "tcn_c6800e67fea33713",
        "tcn_da3ccbe50ebf83ee"
      ]
    },
    "79": {
      "alignment_ids": [],
      "evidence_span_ids": [],
      "node_ids": [
        "tcn_04b053abb78170b2",
        "tcn_1fa1929cf4fa66ce",
        "tcn_b5016353fbe6e3da",
        "tcn_da3ccbe50ebf83ee"
      ]
    },
    "80": {
      "alignment_ids": [],
      "evidence_span_ids": [],
      "node_ids": [
        "tcn_10e45f05668fa751",
        "tcn_1fa1929cf4fa66ce",
        "tcn_b5016353fbe6e3da",
        "tcn_da3ccbe50ebf83ee"
      ]
    },
    "81": {
      "alignment_ids": [],
      "evidence_span_ids": [],
      "node_ids": [
        "tcn_1fa1929cf4fa66ce",
        "tcn_b5016353fbe6e3da",
        "tcn_d929186b6f337ac5",
        "tcn_da3ccbe50ebf83ee"
      ]
    },
    "82": {
      "alignment_ids": [],
      "evidence_span_ids": [],
      "node_ids": [
        "tcn_1fa1929cf4fa66ce",
        "tcn_2acf3a1a20fd2f60",
        "tcn_b5016353fbe6e3da",
        "tcn_da3ccbe50ebf83ee"
      ]
    },
    "83": {
      "alignment_ids": [],
      "evidence_span_ids": [],
      "node_ids": [
        "tcn_1fa1929cf4fa66ce",
        "tcn_42064a5a752c80c1",
        "tcn_b5016353fbe6e3da",
        "tcn_da3ccbe50ebf83ee"
      ]
    },
    "84": {
      "alignment_ids": [],
      "evidence_span_ids": [],
      "node_ids": [
        "tcn_89731140c68a8589",
        "tcn_ec9c9a682cbed8a3"
      ]
    },
    "85": {
      "alignment_ids": [
        "tca_6403d589f7145eb4"
      ],
      "evidence_span_ids": [
        "tes_8139323db9971100"
      ],
      "node_ids": [
        "tcn_6127a960b8c166e4",
        "tcn_73d577fe6d1e9b22",
        "tcn_d25bc944d08b7f17",
        "tcn_ec9c9a682cbed8a3"
      ]
    },
    "86": {
      "alignment_ids": [],
      "evidence_span_ids": [
        "tes_bd300cfeafc73e56",
        "tes_fa3b9fc62bd869bb"
      ],
      "node_ids": [
        "tcn_487644a862e4f415",
        "tcn_6127a960b8c166e4",
        "tcn_71815da86be84270",
        "tcn_8af81bd13524a0fe",
        "tcn_ec9c9a682cbed8a3"
      ]
    },
    "87": {
      "alignment_ids": [],
      "evidence_span_ids": [],
      "node_ids": [
        "tcn_6127a960b8c166e4",
        "tcn_71815da86be84270",
        "tcn_794238daf5b3f066",
        "tcn_ec9c9a682cbed8a3"
      ]
    },
    "88": {
      "alignment_ids": [],
      "evidence_span_ids": [],
      "node_ids": [
        "tcn_34edd8c276a76b6e",
        "tcn_4117fe394b121c56",
        "tcn_71815da86be84270",
        "tcn_ec9c9a682cbed8a3"
      ]
    },
    "89": {
      "alignment_ids": [],
      "evidence_span_ids": [],
      "node_ids": [
        "tcn_34edd8c276a76b6e",
        "tcn_71815da86be84270",
        "tcn_dcc49e871a6aab3e",
        "tcn_ec9c9a682cbed8a3"
      ]
    },
    "90": {
      "alignment_ids": [],
      "evidence_span_ids": [],
      "node_ids": [
        "tcn_34edd8c276a76b6e",
        "tcn_71815da86be84270",
        "tcn_a8317ab43961c836",
        "tcn_ec9c9a682cbed8a3"
      ]
    },
    "91": {
      "alignment_ids": [],
      "evidence_span_ids": [],
      "node_ids": [
        "tcn_34edd8c276a76b6e",
        "tcn_71815da86be84270",
        "tcn_85b77b70a79c7222",
        "tcn_ec9c9a682cbed8a3"
      ]
    },
    "92": {
      "alignment_ids": [],
      "evidence_span_ids": [],
      "node_ids": [
        "tcn_2ee9c204ef2720f8",
        "tcn_34edd8c276a76b6e",
        "tcn_71815da86be84270",
        "tcn_ec9c9a682cbed8a3"
      ]
    },
    "93": {
      "alignment_ids": [
        "tca_28345ce7cbd9c506"
      ],
      "evidence_span_ids": [
        "tes_d0baec0046ac7461"
      ],
      "node_ids": [
        "tcn_16250cbde5a5c651",
        "tcn_2cd1ccce9c00f877",
        "tcn_dfd4ac1adab94bb8",
        "tcn_ec9c9a682cbed8a3"
      ]
    },
    "94": {
      "alignment_ids": [
        "tca_28345ce7cbd9c506"
      ],
      "evidence_span_ids": [
        "tes_d0baec0046ac7461"
      ],
      "node_ids": [
        "tcn_2cd1ccce9c00f877",
        "tcn_38f76ae5be701a9f",
        "tcn_dfd4ac1adab94bb8",
        "tcn_ec9c9a682cbed8a3"
      ]
    },
    "95": {
      "alignment_ids": [
        "tca_28345ce7cbd9c506"
      ],
      "evidence_span_ids": [
        "tes_d0baec0046ac7461"
      ],
      "node_ids": [
        "tcn_2cd1ccce9c00f877",
        "tcn_5e9f9f976363e516",
        "tcn_dfd4ac1adab94bb8",
        "tcn_ec9c9a682cbed8a3"
      ]
    },
    "96": {
      "alignment_ids": [
        "tca_28345ce7cbd9c506"
      ],
      "evidence_span_ids": [
        "tes_d0baec0046ac7461"
      ],
      "node_ids": [
        "tcn_2cd1ccce9c00f877",
        "tcn_435d25b68abe136f",
        "tcn_dfd4ac1adab94bb8",
        "tcn_ec9c9a682cbed8a3"
      ]
    },
    "97": {
      "alignment_ids": [
        "tca_28345ce7cbd9c506"
      ],
      "evidence_span_ids": [
        "tes_d0baec0046ac7461"
      ],
      "node_ids": [
        "tcn_0b4fd4741d247295",
        "tcn_2cd1ccce9c00f877",
        "tcn_dfd4ac1adab94bb8",
        "tcn_ec9c9a682cbed8a3"
      ]
    },
    "98": {
      "alignment_ids": [
        "tca_28345ce7cbd9c506"
      ],
      "evidence_span_ids": [
        "tes_d0baec0046ac7461"
      ],
      "node_ids": [
        "tcn_2a00ca100c3e4c34",
        "tcn_2cd1ccce9c00f877",
        "tcn_dfd4ac1adab94bb8",
        "tcn_ec9c9a682cbed8a3"
      ]
    },
    "99": {
      "alignment_ids": [
        "tca_28345ce7cbd9c506"
      ],
      "evidence_span_ids": [
        "tes_35ea1647625c0f2c",
        "tes_a3ada3a78dba8af6",
        "tes_d0baec0046ac7461",
        "tes_f692c8e9e42730d8"
      ],
      "node_ids": [
        "tcn_16b6df288eda0d92",
        "tcn_2cd1ccce9c00f877",
        "tcn_56a38e609e3c3274",
        "tcn_dfd4ac1adab94bb8",
        "tcn_ec76571e18eb85de",
        "tcn_ec9c9a682cbed8a3",
        "tcn_f9e31f5550fa4c7c"
      ]
    },
    "100": {
      "alignment_ids": [
        "tca_60a6c5fab71a191a"
      ],
      "evidence_span_ids": [
        "tes_f560ac73f175bf65"
      ],
      "node_ids": [
        "tcn_47996f44277ea347",
        "tcn_60a72cc28e5775f0",
        "tcn_ec9c9a682cbed8a3",
        "tcn_ef02f68b7190f993"
      ]
    },
    "101": {
      "alignment_ids": [
        "tca_60a6c5fab71a191a"
      ],
      "evidence_span_ids": [
        "tes_f560ac73f175bf65"
      ],
      "node_ids": [
        "tcn_60a72cc28e5775f0",
        "tcn_d332666d590a52cd",
        "tcn_ec9c9a682cbed8a3",
        "tcn_ef02f68b7190f993"
      ]
    },
    "102": {
      "alignment_ids": [],
      "evidence_span_ids": [
        "tes_a61e5a25eddea5d9"
      ],
      "node_ids": [
        "tcn_60a72cc28e5775f0",
        "tcn_64b0fb5e1c62a769",
        "tcn_bcc3858233f21c10",
        "tcn_ec9c9a682cbed8a3"
      ]
    },
    "103": {
      "alignment_ids": [],
      "evidence_span_ids": [],
      "node_ids": [
        "tcn_16f01f9c8d2938cc",
        "tcn_60a72cc28e5775f0",
        "tcn_64b0fb5e1c62a769",
        "tcn_ec9c9a682cbed8a3"
      ]
    },
    "104": {
      "alignment_ids": [],
      "evidence_span_ids": [],
      "node_ids": [
        "tcn_3c82066e8aba9937",
        "tcn_60a72cc28e5775f0",
        "tcn_64b0fb5e1c62a769",
        "tcn_ec9c9a682cbed8a3"
      ]
    },
    "105": {
      "alignment_ids": [],
      "evidence_span_ids": [],
      "node_ids": [
        "tcn_60a72cc28e5775f0",
        "tcn_64b0fb5e1c62a769",
        "tcn_92b6fc55929c7f4e",
        "tcn_ec9c9a682cbed8a3"
      ]
    },
    "106": {
      "alignment_ids": [],
      "evidence_span_ids": [],
      "node_ids": [
        "tcn_60a72cc28e5775f0",
        "tcn_64b0fb5e1c62a769",
        "tcn_bb2a004379a1f719",
        "tcn_ec9c9a682cbed8a3"
      ]
    },
    "107": {
      "alignment_ids": [],
      "evidence_span_ids": [],
      "node_ids": [
        "tcn_33179ff350a8170d",
        "tcn_64b0fb5e1c62a769",
        "tcn_b1481205142d12e3",
        "tcn_ec9c9a682cbed8a3"
      ]
    },
    "108": {
      "alignment_ids": [],
      "evidence_span_ids": [],
      "node_ids": [
        "tcn_64b0fb5e1c62a769",
        "tcn_b1481205142d12e3",
        "tcn_d6bb9482d715701d",
        "tcn_ec9c9a682cbed8a3"
      ]
    },
    "109": {
      "alignment_ids": [],
      "evidence_span_ids": [
        "tes_2e1e4e852b9c8e33"
      ],
      "node_ids": [
        "tcn_5e1916924c3f1d78",
        "tcn_b1481205142d12e3",
        "tcn_be453802abd582a5",
        "tcn_ec9c9a682cbed8a3"
      ]
    },
    "110": {
      "alignment_ids": [],
      "evidence_span_ids": [],
      "node_ids": [
        "tcn_5e1916924c3f1d78",
        "tcn_71ff5a3a8dd6c1b0",
        "tcn_b1481205142d12e3",
        "tcn_ec9c9a682cbed8a3"
      ]
    },
    "111": {
      "alignment_ids": [],
      "evidence_span_ids": [
        "tes_d63b79f7deeb020b"
      ],
      "node_ids": [
        "tcn_4b00b5c3bb50f47c",
        "tcn_5e1916924c3f1d78",
        "tcn_9777c3c9017e1f62",
        "tcn_b1481205142d12e3",
        "tcn_ec9c9a682cbed8a3"
      ]
    },
    "112": {
      "alignment_ids": [],
      "evidence_span_ids": [],
      "node_ids": [
        "tcn_5e1916924c3f1d78",
        "tcn_b1481205142d12e3",
        "tcn_e84e7feb64dbacd9",
        "tcn_ec9c9a682cbed8a3"
      ]
    },
    "113": {
      "alignment_ids": [],
      "evidence_span_ids": [],
      "node_ids": [
        "tcn_5e1916924c3f1d78",
        "tcn_87fe6a8b39ac44dc",
        "tcn_b1481205142d12e3",
        "tcn_ec9c9a682cbed8a3"
      ]
    },
    "114": {
      "alignment_ids": [],
      "evidence_span_ids": [
        "tes_981be2d659a77838"
      ],
      "node_ids": [
        "tcn_b1481205142d12e3",
        "tcn_d4ae4eebcbc39126",
        "tcn_d900b71e168ae8c2",
        "tcn_ec9c9a682cbed8a3"
      ]
    },
    "115": {
      "alignment_ids": [],
      "evidence_span_ids": [],
      "node_ids": [
        "tcn_6e563d0487904e70",
        "tcn_b1481205142d12e3",
        "tcn_d900b71e168ae8c2",
        "tcn_ec9c9a682cbed8a3"
      ]
    },
    "116": {
      "alignment_ids": [],
      "evidence_span_ids": [],
      "node_ids": [
        "tcn_2e0c3b585ab565b4",
        "tcn_b1481205142d12e3",
        "tcn_d900b71e168ae8c2",
        "tcn_ec9c9a682cbed8a3"
      ]
    },
    "117": {
      "alignment_ids": [],
      "evidence_span_ids": [],
      "node_ids": [
        "tcn_99740f1e131756ef",
        "tcn_b1481205142d12e3",
        "tcn_d900b71e168ae8c2",
        "tcn_ec9c9a682cbed8a3"
      ]
    },
    "118": {
      "alignment_ids": [],
      "evidence_span_ids": [],
      "node_ids": [
        "tcn_b1481205142d12e3",
        "tcn_d900b71e168ae8c2",
        "tcn_ec9c9a682cbed8a3",
        "tcn_f9768decbd207273"
      ]
    },
    "119": {
      "alignment_ids": [],
      "evidence_span_ids": [],
      "node_ids": [
        "tcn_4e5d1c2b055a7a28",
        "tcn_b1481205142d12e3",
        "tcn_d900b71e168ae8c2",
        "tcn_ec9c9a682cbed8a3"
      ]
    },
    "120": {
      "alignment_ids": [],
      "evidence_span_ids": [],
      "node_ids": [
        "tcn_43e777b42aed3f57",
        "tcn_d0d6cef1faf1987e"
      ]
    },
    "121": {
      "alignment_ids": [
        "tca_4644f92b7a13313c",
        "tca_d0ac55da5dd7c916"
      ],
      "evidence_span_ids": [],
      "node_ids": [
        "tcn_850d122d04bf502d",
        "tcn_a87af02e8e2dde09",
        "tcn_d0d6cef1faf1987e"
      ]
    },
    "122": {
      "alignment_ids": [],
      "evidence_span_ids": [],
      "node_ids": [
        "tcn_d0d6cef1faf1987e",
        "tcn_d15314b3f8aa5336",
        "tcn_de0b7bdc91da4f78"
      ]
    },
    "123": {
      "alignment_ids": [],
      "evidence_span_ids": [],
      "node_ids": [
        "tcn_0f21d6c8acc38b50",
        "tcn_d0d6cef1faf1987e",
        "tcn_de0b7bdc91da4f78"
      ]
    },
    "124": {
      "alignment_ids": [],
      "evidence_span_ids": [],
      "node_ids": [
        "tcn_d0d6cef1faf1987e",
        "tcn_de0b7bdc91da4f78",
        "tcn_f090435ea825d81b"
      ]
    },
    "125": {
      "alignment_ids": [],
      "evidence_span_ids": [],
      "node_ids": [
        "tcn_389d4eeff4421430",
        "tcn_d0d6cef1faf1987e",
        "tcn_de0b7bdc91da4f78"
      ]
    },
    "126": {
      "alignment_ids": [],
      "evidence_span_ids": [],
      "node_ids": [
        "tcn_20b19bae28a4b188",
        "tcn_babd1602360cc94c",
        "tcn_d0d6cef1faf1987e"
      ]
    },
    "127": {
      "alignment_ids": [],
      "evidence_span_ids": [],
      "node_ids": [
        "tcn_20b19bae28a4b188",
        "tcn_d0d6cef1faf1987e",
        "tcn_f86294be23609e20"
      ]
    },
    "128": {
      "alignment_ids": [],
      "evidence_span_ids": [],
      "node_ids": [
        "tcn_1133a60a5a56e4d4",
        "tcn_20b19bae28a4b188",
        "tcn_d0d6cef1faf1987e"
      ]
    },
    "129": {
      "alignment_ids": [],
      "evidence_span_ids": [],
      "node_ids": [
        "tcn_20b19bae28a4b188",
        "tcn_b6ea764309cbc1eb",
        "tcn_d0d6cef1faf1987e"
      ]
    },
    "130": {
      "alignment_ids": [],
      "evidence_span_ids": [],
      "node_ids": [
        "tcn_20b19bae28a4b188",
        "tcn_90833b4401abac85",
        "tcn_d0d6cef1faf1987e"
      ]
    },
    "131": {
      "alignment_ids": [],
      "evidence_span_ids": [],
      "node_ids": [
        "tcn_20b19bae28a4b188",
        "tcn_d0d6cef1faf1987e",
        "tcn_f377d4cc86067af1"
      ]
    },
    "132": {
      "alignment_ids": [],
      "evidence_span_ids": [],
      "node_ids": [
        "tcn_8338da4eedf58f93",
        "tcn_d0d6cef1faf1987e",
        "tcn_d9fd0aa9cbd05f58"
      ]
    },
    "133": {
      "alignment_ids": [],
      "evidence_span_ids": [],
      "node_ids": [
        "tcn_8338da4eedf58f93",
        "tcn_b8dedf6cd5fa9044",
        "tcn_d0d6cef1faf1987e"
      ]
    },
    "134": {
      "alignment_ids": [],
      "evidence_span_ids": [],
      "node_ids": [
        "tcn_36b69481b5812728",
        "tcn_8338da4eedf58f93",
        "tcn_d0d6cef1faf1987e"
      ]
    },
    "135": {
      "alignment_ids": [],
      "evidence_span_ids": [],
      "node_ids": [
        "tcn_1813e534e9e6bd3e",
        "tcn_8338da4eedf58f93",
        "tcn_d0d6cef1faf1987e"
      ]
    },
    "136": {
      "alignment_ids": [],
      "evidence_span_ids": [],
      "node_ids": [
        "tcn_67a7124b710609fa",
        "tcn_8338da4eedf58f93",
        "tcn_d0d6cef1faf1987e"
      ]
    },
    "137": {
      "alignment_ids": [],
      "evidence_span_ids": [],
      "node_ids": [
        "tcn_4d706c055c8ae4fb",
        "tcn_8338da4eedf58f93",
        "tcn_d0d6cef1faf1987e"
      ]
    },
    "138": {
      "alignment_ids": [],
      "evidence_span_ids": [],
      "node_ids": [
        "tcn_1c9f2b277275efd4",
        "tcn_8338da4eedf58f93",
        "tcn_d0d6cef1faf1987e"
      ]
    },
    "139": {
      "alignment_ids": [],
      "evidence_span_ids": [],
      "node_ids": [
        "tcn_39ae9f3473dd62be",
        "tcn_d0d6cef1faf1987e",
        "tcn_eeff3011d620004d"
      ]
    },
    "140": {
      "alignment_ids": [],
      "evidence_span_ids": [
        "tes_aab04ef041a7cf8f"
      ],
      "node_ids": [
        "tcn_3e4174abadaf4861",
        "tcn_d0d6cef1faf1987e",
        "tcn_e9bfb4782d669598",
        "tcn_eeff3011d620004d"
      ]
    },
    "141": {
      "alignment_ids": [],
      "evidence_span_ids": [
        "tes_0cd5dcd8693f5dc0",
        "tes_fb92ffd9900e25b3"
      ],
      "node_ids": [
        "tcn_afbdb090aa15f46e",
        "tcn_d093e54ac51e9fa1",
        "tcn_d0d6cef1faf1987e",
        "tcn_d8e60a051054a6bd",
        "tcn_eeff3011d620004d"
      ]
    },
    "142": {
      "alignment_ids": [],
      "evidence_span_ids": [],
      "node_ids": [
        "tcn_c6d98fafba7b75b7",
        "tcn_d093e54ac51e9fa1",
        "tcn_d0d6cef1faf1987e",
        "tcn_eeff3011d620004d"
      ]
    },
    "143": {
      "alignment_ids": [],
      "evidence_span_ids": [],
      "node_ids": [
        "tcn_2a53e9aea8f1ddc0",
        "tcn_d093e54ac51e9fa1",
        "tcn_d0d6cef1faf1987e",
        "tcn_eeff3011d620004d"
      ]
    },
    "144": {
      "alignment_ids": [],
      "evidence_span_ids": [],
      "node_ids": [
        "tcn_1fae9d43dd2337a4",
        "tcn_b464a69185b74f33",
        "tcn_d093e54ac51e9fa1",
        "tcn_d0d6cef1faf1987e"
      ]
    },
    "145": {
      "alignment_ids": [],
      "evidence_span_ids": [],
      "node_ids": [
        "tcn_b464a69185b74f33",
        "tcn_d093e54ac51e9fa1",
        "tcn_d0d6cef1faf1987e",
        "tcn_e2c685ec5de3dca2"
      ]
    },
    "146": {
      "alignment_ids": [],
      "evidence_span_ids": [],
      "node_ids": [
        "tcn_379631cc9fa0bc07",
        "tcn_b464a69185b74f33",
        "tcn_d093e54ac51e9fa1",
        "tcn_d0d6cef1faf1987e"
      ]
    },
    "147": {
      "alignment_ids": [],
      "evidence_span_ids": [],
      "node_ids": [
        "tcn_3052d8ed562156b6",
        "tcn_b464a69185b74f33",
        "tcn_d093e54ac51e9fa1",
        "tcn_d0d6cef1faf1987e"
      ]
    },
    "148": {
      "alignment_ids": [],
      "evidence_span_ids": [],
      "node_ids": [
        "tcn_649a80e4c5321138",
        "tcn_b464a69185b74f33",
        "tcn_d093e54ac51e9fa1",
        "tcn_d0d6cef1faf1987e"
      ]
    },
    "149": {
      "alignment_ids": [
        "tca_583e68ef24afa8cd",
        "tca_bf77c3fd55061414"
      ],
      "evidence_span_ids": [
        "tes_3df3734056c30249",
        "tes_6f1a5b2062c31184",
        "tes_81735ef38a9e0851",
        "tes_cc30bef8aea923e4"
      ],
      "node_ids": [
        "tcn_0a8ee6d0d9d43a04",
        "tcn_34fd8cfbfa2c46b1",
        "tcn_67008e9225335bef",
        "tcn_cb32ff16e3988f58",
        "tcn_d0d6cef1faf1987e",
        "tcn_f50c4fe418d46d2e",
        "tcn_fe20e26275e6852c"
      ]
    },
    "150": {
      "alignment_ids": [],
      "evidence_span_ids": [
        "tes_9c750088f2dfb055"
      ],
      "node_ids": [
        "tcn_0a8ee6d0d9d43a04",
        "tcn_67008e9225335bef",
        "tcn_7c21a5b6b6e99e5f",
        "tcn_d0d6cef1faf1987e",
        "tcn_d7acc06e0a865aa7"
      ]
    },
    "151": {
      "alignment_ids": [],
      "evidence_span_ids": [],
      "node_ids": [
        "tcn_0a8ee6d0d9d43a04",
        "tcn_0b13283e89698df6",
        "tcn_67008e9225335bef",
        "tcn_d0d6cef1faf1987e"
      ]
    },
    "152": {
      "alignment_ids": [],
      "evidence_span_ids": [],
      "node_ids": [
        "tcn_0a8ee6d0d9d43a04",
        "tcn_136e0658777b1314",
        "tcn_67008e9225335bef",
        "tcn_d0d6cef1faf1987e"
      ]
    },
    "153": {
      "alignment_ids": [],
      "evidence_span_ids": [],
      "node_ids": [
        "tcn_0a8ee6d0d9d43a04",
        "tcn_20ca88fe5885c25e",
        "tcn_67008e9225335bef",
        "tcn_d0d6cef1faf1987e"
      ]
    },
    "154": {
      "alignment_ids": [],
      "evidence_span_ids": [],
      "node_ids": [
        "tcn_0a8ee6d0d9d43a04",
        "tcn_67008e9225335bef",
        "tcn_974d6c7e1770ce31",
        "tcn_d0d6cef1faf1987e"
      ]
    },
    "155": {
      "alignment_ids": [],
      "evidence_span_ids": [],
      "node_ids": [
        "tcn_0a8ee6d0d9d43a04",
        "tcn_67008e9225335bef",
        "tcn_c73d1c45c4b8abbe",
        "tcn_d0d6cef1faf1987e"
      ]
    },
    "156": {
      "alignment_ids": [],
      "evidence_span_ids": [],
      "node_ids": [
        "tcn_0a8ee6d0d9d43a04",
        "tcn_67008e9225335bef",
        "tcn_8381611626be1a63",
        "tcn_d0d6cef1faf1987e"
      ]
    },
    "157": {
      "alignment_ids": [],
      "evidence_span_ids": [],
      "node_ids": [
        "tcn_0a8ee6d0d9d43a04",
        "tcn_67008e9225335bef",
        "tcn_993f19bd5ad5aef3",
        "tcn_d0d6cef1faf1987e"
      ]
    },
    "158": {
      "alignment_ids": [],
      "evidence_span_ids": [],
      "node_ids": [
        "tcn_0a8ee6d0d9d43a04",
        "tcn_67008e9225335bef",
        "tcn_b3d8e349c1bfcf06",
        "tcn_d0d6cef1faf1987e"
      ]
    },
    "159": {
      "alignment_ids": [],
      "evidence_span_ids": [],
      "node_ids": [
        "tcn_0a8ee6d0d9d43a04",
        "tcn_4b92049e94bab0c5",
        "tcn_67008e9225335bef",
        "tcn_d0d6cef1faf1987e"
      ]
    },
    "160": {
      "alignment_ids": [],
      "evidence_span_ids": [],
      "node_ids": [
        "tcn_0a8ee6d0d9d43a04",
        "tcn_2978328bd37a7496",
        "tcn_67008e9225335bef",
        "tcn_d0d6cef1faf1987e"
      ]
    },
    "161": {
      "alignment_ids": [],
      "evidence_span_ids": [],
      "node_ids": [
        "tcn_0a8ee6d0d9d43a04",
        "tcn_67008e9225335bef",
        "tcn_d0d6cef1faf1987e"
      ]
    },
    "162": {
      "alignment_ids": [],
      "evidence_span_ids": [],
      "node_ids": [
        "tcn_0a8ee6d0d9d43a04",
        "tcn_67008e9225335bef",
        "tcn_d0d6cef1faf1987e",
        "tcn_da4a29fe9718e3f1"
      ]
    }
  },
  "schema_version": 1
}
